[
  {
    "url": "https://www.airliquide.com/fr",
    "cac40": "airliquide",
    "lh_version": "12.0.0",
    "lh_perf": 62,
    "lh_accessibility": 96,
    "lh_bestpractices": 96,
    "lh_seo": 92,
    "lh_total": 346,
    "FCP": 1.607687499999999,
    "SI": 5.057256663957113,
    "LCP": 3.1232874999999978,
    "TBT": 488.0000000000009,
    "CLS": 0.2920511695768962,
    "TTI": 15.705315899999999,
    "FID": 297,
    "TTFB": 46.05600000000004,
    "total_weight": 3903,
    "media_weight": 1250,
    "image_weight": 1022,
    "script_weight": 153,
    "font_weight": 76,
    "other_weight": 59,
    "stylesheet_weight": 45,
    "document_weight": 0,
    "thirdParty_weight": 1296,
    "carbon_footprint": "E (0.78g)"
  },
  {
    "url": "https://www.airbus.com/en",
    "cac40": "airbus",
    "lh_version": "12.0.0",
    "lh_perf": 61,
    "lh_accessibility": 98,
    "lh_bestpractices": 100,
    "lh_seo": 92,
    "lh_total": 351,
    "FCP": 2.0376725000000007,
    "SI": 3.9835661060061263,
    "LCP": 6.736143000000002,
    "TBT": 314,
    "CLS": 0.14043859511662365,
    "TTI": 11.080691700000001,
    "FID": 163,
    "TTFB": 29.391,
    "total_weight": 4558,
    "media_weight": 2357,
    "image_weight": 815,
    "script_weight": 423,
    "font_weight": 298,
    "other_weight": 85,
    "stylesheet_weight": 42,
    "document_weight": 41,
    "thirdParty_weight": 498,
    "carbon_footprint": "F (3.31g)"
  },
  {
    "url": "https://www.alstom.com/fr",
    "cac40": "alstom",
    "lh_version": "12.0.0",
    "lh_perf": 54,
    "lh_accessibility": 89,
    "lh_bestpractices": 93,
    "lh_seo": 100,
    "lh_total": 336,
    "FCP": 3.5478242,
    "SI": 12.626237918231636,
    "LCP": 32.08830860000002,
    "TBT": 230.5,
    "CLS": 0,
    "TTI": 22.41791340000001,
    "FID": 290,
    "TTFB": 105.08800000000001,
    "total_weight": 7230,
    "media_weight": 6229,
    "image_weight": 404,
    "script_weight": 70,
    "font_weight": 55,
    "other_weight": 45,
    "stylesheet_weight": 43,
    "document_weight": 0,
    "thirdParty_weight": 383,
    "carbon_footprint": "F (1.80g)"
  },
  {
    "url": "https://france.arcelormittal.com/",
    "cac40": "france.arcelormittal",
    "lh_version": "12.0.0",
    "lh_perf": 93,
    "lh_accessibility": 93,
    "lh_bestpractices": 100,
    "lh_seo": 100,
    "lh_total": 386,
    "FCP": 1.217722,
    "SI": 1.4459942047557766,
    "LCP": 3.208722,
    "TBT": 0,
    "CLS": 0,
    "TTI": 1.2177220000000002,
    "FID": 41,
    "TTFB": 48.853,
    "total_weight": 662,
    "media_weight": 473,
    "image_weight": 82,
    "script_weight": 38,
    "font_weight": 30,
    "other_weight": 18,
    "stylesheet_weight": 0,
    "document_weight": 0,
    "thirdParty_weight": 22,
    "carbon_footprint": "B (0.33g)"
  },
  {
    "url": "https://www.axa.com/fr",
    "cac40": "axa",
    "lh_version": "12.0.0",
    "lh_perf": 55,
    "lh_accessibility": 89,
    "lh_bestpractices": 71,
    "lh_seo": 83,
    "lh_total": 298,
    "FCP": 5.0470859254856615,
    "SI": 6.586131754662296,
    "LCP": 17.00906723423219,
    "TBT": 260,
    "CLS": 0.023663816839730567,
    "TTI": 21.274342340554817,
    "FID": 166,
    "TTFB": 415.1,
    "total_weight": 4959,
    "media_weight": 2098,
    "image_weight": 885,
    "script_weight": 691,
    "font_weight": 140,
    "other_weight": 116,
    "stylesheet_weight": 37,
    "document_weight": 0,
    "thirdParty_weight": 993,
    "carbon_footprint": "F (1.05g)"
  },
  {
    "url": "https://group.bnpparibas/",
    "cac40": "group",
    "lh_version": "12.0.0",
    "lh_perf": 76,
    "lh_accessibility": 84,
    "lh_bestpractices": 75,
    "lh_seo": 92,
    "lh_total": 327,
    "FCP": 2.93731205,
    "SI": 3.711525587957361,
    "LCP": 3.9968713199999995,
    "TBT": 260.5,
    "CLS": 0.008443690215537794,
    "TTI": 8.3774222505,
    "FID": 200,
    "TTFB": 22.362,
    "total_weight": 4265,
    "media_weight": 1301,
    "image_weight": 492,
    "script_weight": 216,
    "font_weight": 75,
    "other_weight": 51,
    "stylesheet_weight": 17,
    "document_weight": 0,
    "thirdParty_weight": 2113,
    "carbon_footprint": "D (0.57g)"
  },
  {
    "url": "https://www.bouygues.com/",
    "cac40": "bouygues",
    "lh_version": "12.0.0",
    "lh_perf": 79,
    "lh_accessibility": 97,
    "lh_bestpractices": 96,
    "lh_seo": 100,
    "lh_total": 372,
    "FCP": 2.0923451999999996,
    "SI": 3.0906580355194517,
    "LCP": 3.5939882999999995,
    "TBT": 352.5,
    "CLS": 0.041052565284381524,
    "TTI": 13.33936763373639,
    "FID": 192,
    "TTFB": 37.923,
    "total_weight": 3422,
    "media_weight": 1261,
    "image_weight": 386,
    "script_weight": 161,
    "font_weight": 110,
    "other_weight": 78,
    "stylesheet_weight": 43,
    "document_weight": 0,
    "thirdParty_weight": 1383,
    "carbon_footprint": "D (0.60g)"
  },
  {
    "url": "https://www.capgemini.com/fr-fr/",
    "cac40": "capgemini",
    "lh_version": "12.0.0",
    "lh_perf": 63,
    "lh_accessibility": 93,
    "lh_bestpractices": 57,
    "lh_seo": 77,
    "lh_total": 290,
    "FCP": 2.8559307,
    "SI": 7.220057473888717,
    "LCP": 6.2601841,
    "TBT": 190,
    "CLS": 0.00006920386755589527,
    "TTI": 18.710681489999995,
    "FID": 122,
    "TTFB": 7.024999999999999,
    "total_weight": 4100,
    "media_weight": 1442,
    "image_weight": 1159,
    "script_weight": 570,
    "font_weight": 248,
    "other_weight": 118,
    "stylesheet_weight": 30,
    "document_weight": 0,
    "thirdParty_weight": 533,
    "carbon_footprint": "F (1.20g)"
  },
  {
    "url": "https://www.carrefour.com/fr",
    "cac40": "carrefour",
    "lh_version": "12.0.0",
    "lh_perf": 54,
    "lh_accessibility": 70,
    "lh_bestpractices": 82,
    "lh_seo": 77,
    "lh_total": 283,
    "FCP": 2.9737862,
    "SI": 3.3527188413810216,
    "LCP": 5.2111149,
    "TBT": 240,
    "CLS": 0.3235195154476492,
    "TTI": 9.507343600000002,
    "FID": 227,
    "TTFB": 112.00699999999999,
    "total_weight": 2058,
    "media_weight": 1177,
    "image_weight": 425,
    "script_weight": 92,
    "font_weight": 54,
    "other_weight": 53,
    "stylesheet_weight": 10,
    "document_weight": 0,
    "thirdParty_weight": 247,
    "carbon_footprint": "C (0.48g)"
  },
  {
    "url": "https://www.credit-agricole.com/",
    "cac40": "credit-agricole",
    "lh_version": "12.0.0",
    "lh_perf": 46,
    "lh_accessibility": 79,
    "lh_bestpractices": 82,
    "lh_seo": 92,
    "lh_total": 299,
    "FCP": 3.0145254999999995,
    "SI": 3.1465033033043492,
    "LCP": 12.2887355,
    "TBT": 76.50000000000091,
    "CLS": 0.6699802010089259,
    "TTI": 10.112603575,
    "FID": 110,
    "TTFB": 12.642000000000003,
    "total_weight": 1976,
    "media_weight": 1036,
    "image_weight": 403,
    "script_weight": 212,
    "font_weight": 180,
    "other_weight": 110,
    "stylesheet_weight": 1,
    "document_weight": 0,
    "thirdParty_weight": 33,
    "carbon_footprint": "C (0.47g)"
  },
  {
    "url": "https://www.danone.com/fr.html",
    "cac40": "danone",
    "lh_version": "12.0.0",
    "lh_perf": 46,
    "lh_accessibility": 80,
    "lh_bestpractices": 75,
    "lh_seo": 85,
    "lh_total": 286,
    "FCP": 1.939520961669443,
    "SI": 4.144637107111892,
    "LCP": 15.448641963967553,
    "TBT": 439,
    "CLS": 0.27990263541126,
    "TTI": 15.035278956795612,
    "FID": 234,
    "TTFB": 4.655999999999999,
    "total_weight": 22815,
    "media_weight": 19660,
    "image_weight": 1415,
    "script_weight": 125,
    "font_weight": 97,
    "other_weight": 72,
    "stylesheet_weight": 58,
    "document_weight": 0,
    "thirdParty_weight": 1388,
    "carbon_footprint": "D (0.65g)"
  },
  {
    "url": "https://www.3ds.com/fr/",
    "cac40": "3ds",
    "lh_version": "12.0.0",
    "lh_perf": 42,
    "lh_accessibility": 85,
    "lh_bestpractices": 79,
    "lh_seo": 92,
    "lh_total": 298,
    "FCP": 3.07603,
    "SI": 5.2633112043755865,
    "LCP": 6.621077499999999,
    "TBT": 878,
    "CLS": 0.14016330306677052,
    "TTI": 20.343690999999993,
    "FID": 225,
    "TTFB": 75.124,
    "total_weight": 9485,
    "media_weight": 3823,
    "image_weight": 2811,
    "script_weight": 1447,
    "font_weight": 286,
    "other_weight": 156,
    "stylesheet_weight": 77,
    "document_weight": 63,
    "thirdParty_weight": 823,
    "carbon_footprint": "F (2.28g)"
  },
  {
    "url": "https://www.edenred.com/fr",
    "cac40": "edenred",
    "lh_version": "12.0.0",
    "lh_perf": 53,
    "lh_accessibility": 97,
    "lh_bestpractices": 100,
    "lh_seo": 100,
    "lh_total": 350,
    "FCP": 1.8202396,
    "SI": 5.456686513442813,
    "LCP": 8.388441199999999,
    "TBT": 169,
    "CLS": 0.2909456120813325,
    "TTI": 6.23184356,
    "FID": 215,
    "TTFB": 54.071999999999996,
    "total_weight": 1656,
    "media_weight": 599,
    "image_weight": 482,
    "script_weight": 245,
    "font_weight": 36,
    "other_weight": 26,
    "stylesheet_weight": 19,
    "document_weight": 0,
    "thirdParty_weight": 249,
    "carbon_footprint": "B (0.36g)"
  },
  {
    "url": "https://www.engie.com/",
    "cac40": "engie",
    "lh_version": "12.0.0",
    "lh_perf": 53,
    "lh_accessibility": 68,
    "lh_bestpractices": 100,
    "lh_seo": 92,
    "lh_total": 313,
    "FCP": 3.6964718,
    "SI": 3.9411462627410248,
    "LCP": 13.724014599999999,
    "TBT": 150.5,
    "CLS": 0.22888461515747888,
    "TTI": 14.8809722,
    "FID": 212,
    "TTFB": 5.122,
    "total_weight": 4076,
    "media_weight": 2640,
    "image_weight": 701,
    "script_weight": 202,
    "font_weight": 60,
    "other_weight": 17,
    "stylesheet_weight": 1,
    "document_weight": 0,
    "thirdParty_weight": 455,
    "carbon_footprint": "F (0.90g)"
  },
  {
    "url": "https://www.essilorluxottica.com/fr/",
    "cac40": "essilorluxottica",
    "lh_version": "12.0.0",
    "lh_perf": 57,
    "lh_accessibility": 91,
    "lh_bestpractices": 79,
    "lh_seo": 92,
    "lh_total": 319,
    "FCP": 1.0310408,
    "SI": 6.1738167065412926,
    "LCP": 6.4636055,
    "TBT": 597.5000000000005,
    "CLS": 0,
    "TTI": 9.082489169999999,
    "FID": 394.0000000000009,
    "TTFB": 110.35499999999999,
    "total_weight": 4824,
    "media_weight": 2515,
    "image_weight": 1423,
    "script_weight": 561,
    "font_weight": 67,
    "other_weight": 32,
    "stylesheet_weight": 7,
    "document_weight": 4,
    "thirdParty_weight": 215,
    "carbon_footprint": "F (2.58g)"
  },
  {
    "url": "https://www.eurofins.com/",
    "cac40": "eurofins",
    "lh_version": "12.0.0",
    "lh_perf": 71,
    "lh_accessibility": 84,
    "lh_bestpractices": 96,
    "lh_seo": 75,
    "lh_total": 326,
    "FCP": 3.0581529117666895,
    "SI": 3.0581529117666895,
    "LCP": 6.985478913401887,
    "TBT": 24.5,
    "CLS": 0.0001448615547818489,
    "TTI": 8.550640163078224,
    "FID": 84,
    "TTFB": 73.50599999999999,
    "total_weight": 1915,
    "media_weight": 706,
    "image_weight": 347,
    "script_weight": 279,
    "font_weight": 78,
    "other_weight": 62,
    "stylesheet_weight": 42,
    "document_weight": 0,
    "thirdParty_weight": 401,
    "carbon_footprint": "C (0.50g)"
  },
  {
    "url": "",
    "cac40": "",
    "lh_version": "",
    "lh_perf": 0,
    "lh_accessibility": 0,
    "lh_bestpractices": 0,
    "lh_seo": 0,
    "lh_total": 0,
    "FCP": 0,
    "SI": 0,
    "LCP": 0,
    "TBT": 0,
    "CLS": 0,
    "TTI": 0,
    "FID": 0,
    "TTFB": 0,
    "total_weight": 0,
    "media_weight": 0,
    "image_weight": 0,
    "script_weight": 0,
    "font_weight": 0,
    "other_weight": 0,
    "stylesheet_weight": 0,
    "document_weight": 0,
    "thirdParty_weight": 0,
    "carbon_footprint": "---"
  },
  {
    "url": "https://www.legrandgroup.com/fr",
    "cac40": "legrandgroup",
    "lh_version": "12.0.0",
    "lh_perf": 70,
    "lh_accessibility": 69,
    "lh_bestpractices": 79,
    "lh_seo": 100,
    "lh_total": 318,
    "FCP": 2.1492801999999993,
    "SI": 3.4570808433558216,
    "LCP": 6.965843849999998,
    "TBT": 198.5,
    "CLS": 0.003299714300583616,
    "TTI": 6.919790734999999,
    "FID": 412,
    "TTFB": 64.835,
    "total_weight": 1366,
    "media_weight": 556,
    "image_weight": 251,
    "script_weight": 206,
    "font_weight": 47,
    "other_weight": 23,
    "stylesheet_weight": 5,
    "document_weight": 0,
    "thirdParty_weight": 279,
    "carbon_footprint": "B (0.32g)"
  },
  {
    "url": "https://www.loreal.com/fr/",
    "cac40": "loreal",
    "lh_version": "12.0.0",
    "lh_perf": 68,
    "lh_accessibility": 81,
    "lh_bestpractices": 75,
    "lh_seo": 83,
    "lh_total": 307,
    "FCP": 1.7196861,
    "SI": 2.832482286551402,
    "LCP": 5.781327699999999,
    "TBT": 399,
    "CLS": 0.011935115726626205,
    "TTI": 7.63530691,
    "FID": 285,
    "TTFB": 83.501,
    "total_weight": 1217,
    "media_weight": 439,
    "image_weight": 256,
    "script_weight": 115,
    "font_weight": 39,
    "other_weight": 34,
    "stylesheet_weight": 20,
    "document_weight": 0,
    "thirdParty_weight": 313,
    "carbon_footprint": "B (0.27g)"
  },
  {
    "url": "https://www.lvmh.com/fr",
    "cac40": "lvmh",
    "lh_version": "12.0.0",
    "lh_perf": 32,
    "lh_accessibility": 95,
    "lh_bestpractices": 79,
    "lh_seo": 92,
    "lh_total": 298,
    "FCP": 3.4818453000000003,
    "SI": 9.372003340287,
    "LCP": 12.866390100000002,
    "TBT": 1943.5324499999933,
    "CLS": 0.010560599058950673,
    "TTI": 21.141213055,
    "FID": 738,
    "TTFB": 95.282,
    "total_weight": 4130,
    "media_weight": 1468,
    "image_weight": 856,
    "script_weight": 533,
    "font_weight": 169,
    "other_weight": 49,
    "stylesheet_weight": 33,
    "document_weight": 0,
    "thirdParty_weight": 1020,
    "carbon_footprint": "D (0.74g)"
  },
  {
    "url": "https://www.michelin.com/",
    "cac40": "michelin",
    "lh_version": "12.0.0",
    "lh_perf": 61,
    "lh_accessibility": 91,
    "lh_bestpractices": 96,
    "lh_seo": 100,
    "lh_total": 348,
    "FCP": 2.8171031,
    "SI": 5.303063607258823,
    "LCP": 7.985142800000003,
    "TBT": 291.5,
    "CLS": 0.014820140646110414,
    "TTI": 10.828124955000003,
    "FID": 312,
    "TTFB": 635.4150000000001,
    "total_weight": 7000,
    "media_weight": 1253,
    "image_weight": 849,
    "script_weight": 723,
    "font_weight": 386,
    "other_weight": 204,
    "stylesheet_weight": 64,
    "document_weight": 43,
    "thirdParty_weight": 3478,
    "carbon_footprint": "F (2.55g)"
  },
  {
    "url": "https://www.orange.com/fr",
    "cac40": "orange",
    "lh_version": "12.0.0",
    "lh_perf": 0,
    "lh_accessibility": 93,
    "lh_bestpractices": 96,
    "lh_seo": 85,
    "lh_total": 274,
    "FCP": 2.4271972500000003,
    "SI": 16.36477537245374,
    "LCP": null,
    "TBT": 160.5,
    "CLS": 0.029076722475197304,
    "TTI": 9.872417125000004,
    "FID": 136,
    "TTFB": 11.240999999999985,
    "total_weight": 1543,
    "media_weight": 1036,
    "image_weight": 153,
    "script_weight": 21,
    "font_weight": 17,
    "other_weight": 0,
    "stylesheet_weight": 0,
    "document_weight": 0,
    "thirdParty_weight": 317,
    "carbon_footprint": "C (0.46g)"
  },
  {
    "url": "https://www.pernod-ricard.com/fr",
    "cac40": "pernod-ricard",
    "lh_version": "12.0.0",
    "lh_perf": 64,
    "lh_accessibility": 86,
    "lh_bestpractices": 96,
    "lh_seo": 100,
    "lh_total": 346,
    "FCP": 2.0894706,
    "SI": 3.208151889161075,
    "LCP": 18.122148449999997,
    "TBT": 363,
    "CLS": 0,
    "TTI": 11.014239854876152,
    "FID": 313,
    "TTFB": 23.863,
    "total_weight": 4131,
    "media_weight": 1230,
    "image_weight": 1018,
    "script_weight": 927,
    "font_weight": 343,
    "other_weight": 149,
    "stylesheet_weight": 26,
    "document_weight": 0,
    "thirdParty_weight": 438,
    "carbon_footprint": "F (1.24g)"
  },
  {
    "url": "https://www.publicisgroupe.com/fr/splash",
    "cac40": "publicisgroupe",
    "lh_version": "12.0.0",
    "lh_perf": 59,
    "lh_accessibility": 86,
    "lh_bestpractices": 75,
    "lh_seo": 92,
    "lh_total": 312,
    "FCP": 4.883861399999998,
    "SI": 5.866938222210049,
    "LCP": 14.284904699999993,
    "TBT": 80,
    "CLS": 0.09143196741650281,
    "TTI": 13.538230879999997,
    "FID": 140,
    "TTFB": 14.47,
    "total_weight": 2656,
    "media_weight": 1084,
    "image_weight": 673,
    "script_weight": 380,
    "font_weight": 169,
    "other_weight": 23,
    "stylesheet_weight": 4,
    "document_weight": 0,
    "thirdParty_weight": 324,
    "carbon_footprint": "D (0.61g)"
  },
  {
    "url": "https://www.renaultgroup.com/",
    "cac40": "renaultgroup",
    "lh_version": "12.0.0",
    "lh_perf": 62,
    "lh_accessibility": 87,
    "lh_bestpractices": 100,
    "lh_seo": 100,
    "lh_total": 349,
    "FCP": 1.8384509999999998,
    "SI": 4.702312120210853,
    "LCP": 5.437988300000001,
    "TBT": 547.4999999999982,
    "CLS": 0,
    "TTI": 15.901520010000004,
    "FID": 235.99999999999818,
    "TTFB": 58.333999999999996,
    "total_weight": 4424,
    "media_weight": 1462,
    "image_weight": 1300,
    "script_weight": 316,
    "font_weight": 144,
    "other_weight": 53,
    "stylesheet_weight": 45,
    "document_weight": 0,
    "thirdParty_weight": 1105,
    "carbon_footprint": "F (1.13g)"
  },
  {
    "url": "https://www.safran-group.com/fr",
    "cac40": "safran-group",
    "lh_version": "12.0.0",
    "lh_perf": 78,
    "lh_accessibility": 97,
    "lh_bestpractices": 100,
    "lh_seo": 100,
    "lh_total": 375,
    "FCP": 1.7283191999999998,
    "SI": 3.4706004419920746,
    "LCP": 3.1328123999999997,
    "TBT": 68,
    "CLS": 0.2533558608071707,
    "TTI": 6.524963199999998,
    "FID": 115,
    "TTFB": 361.466,
    "total_weight": 4506,
    "media_weight": 2557,
    "image_weight": 779,
    "script_weight": 691,
    "font_weight": 138,
    "other_weight": 138,
    "stylesheet_weight": 24,
    "document_weight": 0,
    "thirdParty_weight": 178,
    "carbon_footprint": "F (4.33g)"
  },
  {
    "url": "https://www.saint-gobain.com/fr",
    "cac40": "saint-gobain",
    "lh_version": "12.0.0",
    "lh_perf": 72,
    "lh_accessibility": 92,
    "lh_bestpractices": 100,
    "lh_seo": 100,
    "lh_total": 364,
    "FCP": 1.863735,
    "SI": 2.178621029576352,
    "LCP": 8.4158392,
    "TBT": 152,
    "CLS": 0,
    "TTI": 7.60751468,
    "FID": 153,
    "TTFB": 84.536,
    "total_weight": 2887,
    "media_weight": 1460,
    "image_weight": 358,
    "script_weight": 141,
    "font_weight": 103,
    "other_weight": 54,
    "stylesheet_weight": 43,
    "document_weight": 0,
    "thirdParty_weight": 729,
    "carbon_footprint": "D (0.63g)"
  },
  {
    "url": "https://www.sanofi.fr/fr",
    "cac40": "sanofi",
    "lh_version": "12.0.0",
    "lh_perf": 61,
    "lh_accessibility": 100,
    "lh_bestpractices": 100,
    "lh_seo": 100,
    "lh_total": 361,
    "FCP": 0.9416477999999999,
    "SI": 4.133921207253224,
    "LCP": 7.230934950000001,
    "TBT": 537.9999999999995,
    "CLS": 0.010027250527905249,
    "TTI": 7.144767170000001,
    "FID": 259.99999999999955,
    "TTFB": 633.313,
    "total_weight": 1483,
    "media_weight": 717,
    "image_weight": 316,
    "script_weight": 56,
    "font_weight": 37,
    "other_weight": 33,
    "stylesheet_weight": 0,
    "document_weight": 0,
    "thirdParty_weight": 325,
    "carbon_footprint": "B (0.30g)"
  },
  {
    "url": "https://www.se.com/fr/fr/",
    "cac40": "se",
    "lh_version": "12.0.0",
    "lh_perf": 73,
    "lh_accessibility": 88,
    "lh_bestpractices": 79,
    "lh_seo": 100,
    "lh_total": 340,
    "FCP": 2.0486435000000003,
    "SI": 8.773164809123156,
    "LCP": 3.50101605,
    "TBT": 354,
    "CLS": 0.05045586497904024,
    "TTI": 27.86647168999999,
    "FID": 178,
    "TTFB": 46.883,
    "total_weight": 9042,
    "media_weight": 7320,
    "image_weight": 683,
    "script_weight": 123,
    "font_weight": 68,
    "other_weight": 29,
    "stylesheet_weight": 10,
    "document_weight": 0,
    "thirdParty_weight": 808,
    "carbon_footprint": "F (1.48g)"
  },
  {
    "url": "https://www.societegenerale.com/fr",
    "cac40": "societegenerale",
    "lh_version": "12.0.0",
    "lh_perf": 69,
    "lh_accessibility": 93,
    "lh_bestpractices": 96,
    "lh_seo": 100,
    "lh_total": 358,
    "FCP": 1.3867652000000001,
    "SI": 5.776623606025565,
    "LCP": 21.759959400000003,
    "TBT": 51.5,
    "CLS": 0.06682867557715674,
    "TTI": 17.37035104,
    "FID": 87,
    "TTFB": 9.555999999999997,
    "total_weight": 7139,
    "media_weight": 5637,
    "image_weight": 657,
    "script_weight": 294,
    "font_weight": 43,
    "other_weight": 18,
    "stylesheet_weight": 13,
    "document_weight": 0,
    "thirdParty_weight": 478,
    "carbon_footprint": "F (1.72g)"
  },
  {
    "url": "https://www.stellantis.com/fr",
    "cac40": "stellantis",
    "lh_version": "12.0.0",
    "lh_perf": 70,
    "lh_accessibility": 98,
    "lh_bestpractices": 82,
    "lh_seo": 92,
    "lh_total": 342,
    "FCP": 2.3628937,
    "SI": 3.8175948234228034,
    "LCP": 10.718994900000002,
    "TBT": 67.5,
    "CLS": 0.008441897139459283,
    "TTI": 7.06552044,
    "FID": 141,
    "TTFB": 19.27799999999999,
    "total_weight": 20971,
    "media_weight": 16284,
    "image_weight": 3434,
    "script_weight": 208,
    "font_weight": 189,
    "other_weight": 173,
    "stylesheet_weight": 64,
    "document_weight": 58,
    "thirdParty_weight": 561,
    "carbon_footprint": "F (1.08g)"
  },
  {
    "url": "https://www.st.com/content/st_com/en.html",
    "cac40": "st",
    "lh_version": "12.0.0",
    "lh_perf": 42,
    "lh_accessibility": 87,
    "lh_bestpractices": 57,
    "lh_seo": 77,
    "lh_total": 263,
    "FCP": 2.8672560000000002,
    "SI": 5.510264903897629,
    "LCP": 13.999217999999999,
    "TBT": 1202.9999999999982,
    "CLS": 0,
    "TTI": 14.643673880000001,
    "FID": 452.9999999999982,
    "TTFB": 113.838,
    "total_weight": 2482,
    "media_weight": 1352,
    "image_weight": 283,
    "script_weight": 280,
    "font_weight": 148,
    "other_weight": 57,
    "stylesheet_weight": 23,
    "document_weight": 0,
    "thirdParty_weight": 340,
    "carbon_footprint": "F (1.42g)"
  },
  {
    "url": "https://www.teleperformance.com/en-us/locations/france-site/france/",
    "cac40": "teleperformance",
    "lh_version": "12.0.0",
    "lh_perf": 34,
    "lh_accessibility": 61,
    "lh_bestpractices": 79,
    "lh_seo": 83,
    "lh_total": 257,
    "FCP": 3.2896213000000007,
    "SI": 7.712337290908497,
    "LCP": 20.43559184999999,
    "TBT": 315,
    "CLS": 0.5007347833606468,
    "TTI": 22.936547639999986,
    "FID": 129,
    "TTFB": 791.128,
    "total_weight": 7224,
    "media_weight": 5676,
    "image_weight": 461,
    "script_weight": 406,
    "font_weight": 132,
    "other_weight": 94,
    "stylesheet_weight": 27,
    "document_weight": 0,
    "thirdParty_weight": 428,
    "carbon_footprint": "F (1.90g)"
  },
  {
    "url": "https://www.thalesgroup.com/fr",
    "cac40": "thalesgroup",
    "lh_version": "12.0.0",
    "lh_perf": 40,
    "lh_accessibility": 88,
    "lh_bestpractices": 57,
    "lh_seo": 100,
    "lh_total": 285,
    "FCP": 2.5211018000000003,
    "SI": 10.47281265623648,
    "LCP": 21.983871049999998,
    "TBT": 1011.5,
    "CLS": 0,
    "TTI": 33.16756065591152,
    "FID": 425,
    "TTFB": 25.885000000000005,
    "total_weight": 12324,
    "media_weight": 3849,
    "image_weight": 2226,
    "script_weight": 291,
    "font_weight": 248,
    "other_weight": 219,
    "stylesheet_weight": 112,
    "document_weight": 0,
    "thirdParty_weight": 5378,
    "carbon_footprint": "F (2.21g)"
  },
  {
    "url": "https://totalenergies.com/fr",
    "cac40": "totalenergies",
    "lh_version": "12.0.0",
    "lh_perf": 63,
    "lh_accessibility": 89,
    "lh_bestpractices": 71,
    "lh_seo": 100,
    "lh_total": 323,
    "FCP": 2.3178092,
    "SI": 2.3178092,
    "LCP": 7.059179800000002,
    "TBT": 33.499999999999545,
    "CLS": 0.22433309019048508,
    "TTI": 4.52033302,
    "FID": 113,
    "TTFB": 70.063,
    "total_weight": 1208,
    "media_weight": 316,
    "image_weight": 313,
    "script_weight": 244,
    "font_weight": 111,
    "other_weight": 15,
    "stylesheet_weight": 2,
    "document_weight": 0,
    "thirdParty_weight": 206,
    "carbon_footprint": "B (0.37g)"
  },
  {
    "url": "https://www.urw.com/fr-fr",
    "cac40": "urw",
    "lh_version": "12.0.0",
    "lh_perf": 65,
    "lh_accessibility": 64,
    "lh_bestpractices": 100,
    "lh_seo": 92,
    "lh_total": 321,
    "FCP": 4.776863747309272,
    "SI": 4.846622195410078,
    "LCP": 5.833828519730736,
    "TBT": 125.5,
    "CLS": 0.0005636487955789279,
    "TTI": 9.985871049203716,
    "FID": 224,
    "TTFB": 82.485,
    "total_weight": 25880,
    "media_weight": 21552,
    "image_weight": 2633,
    "script_weight": 427,
    "font_weight": 260,
    "other_weight": 102,
    "stylesheet_weight": 102,
    "document_weight": 3,
    "thirdParty_weight": 801,
    "carbon_footprint": "D (0.65g)"
  },
  {
    "url": "https://www.veolia.com/fr",
    "cac40": "veolia",
    "lh_version": "12.0.0",
    "lh_perf": 38,
    "lh_accessibility": 79,
    "lh_bestpractices": 71,
    "lh_seo": 83,
    "lh_total": 271,
    "FCP": 3.974979,
    "SI": 6.069993203715629,
    "LCP": 7.465150000000003,
    "TBT": 1002.4999999999982,
    "CLS": 0.10201735419567154,
    "TTI": 17.523236410000006,
    "FID": 243,
    "TTFB": 125.023,
    "total_weight": 4446,
    "media_weight": 1407,
    "image_weight": 432,
    "script_weight": 420,
    "font_weight": 321,
    "other_weight": 100,
    "stylesheet_weight": 96,
    "document_weight": 0,
    "thirdParty_weight": 1670,
    "carbon_footprint": "A+ (0.07g)"
  },
  {
    "url": "https://www.vinci.com/",
    "cac40": "vinci",
    "lh_version": "12.0.0",
    "lh_perf": 95,
    "lh_accessibility": 83,
    "lh_bestpractices": 100,
    "lh_seo": 100,
    "lh_total": 378,
    "FCP": 1.20998,
    "SI": 1.7642440908280306,
    "LCP": 2.10998,
    "TBT": 10,
    "CLS": 0.11211557383936921,
    "TTI": 2.65998,
    "FID": 70,
    "TTFB": 129.392,
    "total_weight": 1338,
    "media_weight": 956,
    "image_weight": 205,
    "script_weight": 122,
    "font_weight": 32,
    "other_weight": 23,
    "stylesheet_weight": 1,
    "document_weight": 0,
    "thirdParty_weight": 0,
    "carbon_footprint": "B (0.27g)"
  },
  {
    "url": "https://www.vivendi.com/",
    "cac40": "vivendi",
    "lh_version": "12.0.0",
    "lh_perf": 66,
    "lh_accessibility": 88,
    "lh_bestpractices": 96,
    "lh_seo": 69,
    "lh_total": 319,
    "FCP": 4.0271422,
    "SI": 4.0271422,
    "LCP": 7.9483858,
    "TBT": 66.5,
    "CLS": 0,
    "TTI": 5.144790790000001,
    "FID": 183,
    "TTFB": 61.007999999999996,
    "total_weight": 1203,
    "media_weight": 512,
    "image_weight": 272,
    "script_weight": 111,
    "font_weight": 84,
    "other_weight": 18,
    "stylesheet_weight": 1,
    "document_weight": 0,
    "thirdParty_weight": 204,
    "carbon_footprint": "B (0.28g)"
  }
]