[
  {
    "url": "https://www.stellantis.com/fr/responsabilite/dialogue-parties-prenantes",
    "requestedUrl": "https://www.stellantis.com/fr/responsabilite/dialogue-parties-prenantes",
    "timestamp": 1707633272542,
    "ranks": {
      "hundos": 1,
      "performance": 7,
      "accessibility": 8,
      "cumulative": 1
    },
    "lighthouse": {
      "version": "11.5.0",
      "performance": 0.74,
      "accessibility": 1,
      "bestPractices": 0.81,
      "seo": 0.91,
      "total": 346
    },
    "firstContentfulPaint": 2482.1369999999997,
    "firstMeaningfulPaint": 2482.1369999999997,
    "speedIndex": 2827.8731310653143,
    "largestContentfulPaint": 5833.686,
    "totalBlockingTime": 62.5,
    "cumulativeLayoutShift": 0.06678402560875646,
    "timeToInteractive": 8138.637500000001,
    "maxPotentialFirstInputDelay": 106,
    "timeToFirstByte": 29.766000000000005,
    "weight": {
      "summary": "43 requests • 1,1 MiB",
      "total": 1107005,
      "image": 414349,
      "imageCount": 3,
      "script": 203236,
      "scriptCount": 10,
      "document": 189753,
      "font": 178156,
      "fontCount": 12,
      "stylesheet": 57103,
      "stylesheetCount": 9,
      "thirdParty": 565408,
      "thirdPartyCount": 7
    },
    "run": {
      "number": 2,
      "total": 3
    },
    "sidequests": {
      "-weight.total": 1,
      "+weight.total": 47,
      "-weight.document": 4,
      "+weight.document": 44,
      "-weight.script": 2,
      "+weight.script": 33,
      "-weight.image": 2,
      "+weight.image": 41,
      "-weight.font": 1,
      "+weight.font": 39,
      "+weight.fontCount": 7,
      "-timeToFirstByte": 18,
      "-totalBlockingTime": 21,
      "-largestContentfulPaint": 4
    },
    "axe": {
      "passes": 511,
      "violations": 3
    }
  },
  {
    "url": "https://www.stellantis.com/fr/actualite/communiques-de-presse/2022/octobre/stellantis-hordain-premiere-usine-au-monde-a-produire-des-utilitaires-a-hydrogene-electriques-et-thermiques",
    "requestedUrl": "https://www.stellantis.com/fr/actualite/communiques-de-presse/2022/octobre/stellantis-hordain-premiere-usine-au-monde-a-produire-des-utilitaires-a-hydrogene-electriques-et-thermiques",
    "timestamp": 1707634013020,
    "ranks": {
      "hundos": 2,
      "performance": 1,
      "accessibility": 11,
      "cumulative": 2
    },
    "lighthouse": {
      "version": "11.5.0",
      "performance": 0.75,
      "accessibility": 0.98,
      "bestPractices": 0.81,
      "seo": 0.91,
      "total": 345
    },
    "firstContentfulPaint": 2247.0789999999997,
    "firstMeaningfulPaint": 2247.0789999999997,
    "speedIndex": 2765.430770198814,
    "largestContentfulPaint": 6072.379,
    "totalBlockingTime": 39,
    "cumulativeLayoutShift": 0.01954110088807999,
    "timeToInteractive": 7816.790999999997,
    "maxPotentialFirstInputDelay": 107,
    "timeToFirstByte": 40.751999999999995,
    "weight": {
      "summary": "63 requests • 4,6 MiB",
      "total": 4849129,
      "image": 4069158,
      "imageCount": 14,
      "script": 203414,
      "scriptCount": 10,
      "document": 193052,
      "font": 260701,
      "fontCount": 17,
      "stylesheet": 57102,
      "stylesheetCount": 9,
      "thirdParty": 649433,
      "thirdPartyCount": 8
    },
    "run": {
      "number": 3,
      "total": 3
    },
    "sidequests": {
      "-weight.total": 40,
      "+weight.total": 8,
      "-weight.document": 26,
      "+weight.document": 22,
      "-weight.script": 18,
      "+weight.script": 17,
      "-weight.image": 35,
      "+weight.image": 8,
      "-weight.font": 38,
      "+weight.font": 2,
      "+weight.fontCount": 2,
      "-timeToFirstByte": 29,
      "-totalBlockingTime": 6,
      "-largestContentfulPaint": 15
    },
    "axe": {
      "passes": 775,
      "violations": 4
    }
  },
  {
    "url": "https://www.stellantis.com/fr/actualite/communiques-de-presse/2023/novembre/stellantis-annonce-le-rachat-de-934-millions-d-euros-d-actions-a-dongfeng-conformement-au-contrat-cadre-de-rachat-d-actions-signe",
    "requestedUrl": "https://www.stellantis.com/fr/actualite/communiques-de-presse/2023/novembre/stellantis-annonce-le-rachat-de-934-millions-d-euros-d-actions-a-dongfeng-conformement-au-contrat-cadre-de-rachat-d-actions-signe",
    "timestamp": 1707633878763,
    "ranks": {
      "hundos": 3,
      "performance": 4,
      "accessibility": 31,
      "cumulative": 3
    },
    "lighthouse": {
      "version": "11.5.0",
      "performance": 0.75,
      "accessibility": 0.98,
      "bestPractices": 0.81,
      "seo": 0.91,
      "total": 345
    },
    "firstContentfulPaint": 2304.0219999999995,
    "firstMeaningfulPaint": 2304.0219999999995,
    "speedIndex": 3402.453490758161,
    "largestContentfulPaint": 5968.729,
    "totalBlockingTime": 44,
    "cumulativeLayoutShift": 0.0014842675486953772,
    "timeToInteractive": 8400.426000000001,
    "maxPotentialFirstInputDelay": 107,
    "timeToFirstByte": 17.436,
    "weight": {
      "summary": "52 requests • 1,1 MiB",
      "total": 1202379,
      "image": 440756,
      "imageCount": 8,
      "script": 203422,
      "scriptCount": 10,
      "document": 191770,
      "font": 244859,
      "fontCount": 16,
      "stylesheet": 57101,
      "stylesheetCount": 9,
      "thirdParty": 632364,
      "thirdPartyCount": 7
    },
    "run": {
      "number": 3,
      "total": 3
    },
    "sidequests": {
      "-weight.total": 13,
      "+weight.total": 35,
      "-weight.document": 17,
      "+weight.document": 31,
      "-weight.script": 24,
      "+weight.script": 11,
      "-weight.image": 9,
      "+weight.image": 34,
      "-weight.font": 26,
      "+weight.font": 14,
      "+weight.fontCount": 3,
      "-timeToFirstByte": 12,
      "-totalBlockingTime": 10,
      "-largestContentfulPaint": 9
    },
    "axe": {
      "passes": 682,
      "violations": 4
    }
  },
  {
    "url": "https://www.stellantis.com/fr/actualite/communiques-de-presse/2024/janvier/renforcer-le-pouvoir-clients-une-annee-de-progres-majeurs-dans-la-data-de-mobilite-pour-mobilisights",
    "requestedUrl": "https://www.stellantis.com/fr/actualite/communiques-de-presse/2024/janvier/renforcer-le-pouvoir-clients-une-annee-de-progres-majeurs-dans-la-data-de-mobilite-pour-mobilisights",
    "timestamp": 1707633868788,
    "ranks": {
      "hundos": 4,
      "performance": 3,
      "accessibility": 19,
      "cumulative": 4
    },
    "lighthouse": {
      "version": "11.5.0",
      "performance": 0.75,
      "accessibility": 0.98,
      "bestPractices": 0.81,
      "seo": 0.91,
      "total": 345
    },
    "firstContentfulPaint": 2308.809,
    "firstMeaningfulPaint": 2308.809,
    "speedIndex": 3180.066085133766,
    "largestContentfulPaint": 5736.948000000001,
    "totalBlockingTime": 75.5,
    "cumulativeLayoutShift": 0.025687344628143666,
    "timeToInteractive": 8437.2625,
    "maxPotentialFirstInputDelay": 107,
    "timeToFirstByte": 17.113,
    "weight": {
      "summary": "52 requests • 1,2 MiB",
      "total": 1282278,
      "image": 519434,
      "imageCount": 8,
      "script": 203426,
      "scriptCount": 10,
      "document": 193013,
      "font": 244859,
      "fontCount": 16,
      "stylesheet": 57101,
      "stylesheetCount": 9,
      "thirdParty": 632339,
      "thirdPartyCount": 7
    },
    "run": {
      "number": 3,
      "total": 3
    },
    "sidequests": {
      "-weight.total": 23,
      "+weight.total": 25,
      "-weight.document": 25,
      "+weight.document": 23,
      "-weight.script": 28,
      "+weight.script": 7,
      "-weight.image": 18,
      "+weight.image": 25,
      "-weight.font": 26,
      "+weight.font": 14,
      "+weight.fontCount": 3,
      "-timeToFirstByte": 10,
      "-totalBlockingTime": 30,
      "-largestContentfulPaint": 3
    },
    "axe": {
      "passes": 707,
      "violations": 4
    }
  },
  {
    "url": "https://www.stellantis.com/fr/talent/rejoignez-nos-talents",
    "requestedUrl": "https://www.stellantis.com/fr/talent/nos-competences",
    "timestamp": 1707633818008,
    "ranks": {
      "hundos": 5,
      "performance": 22,
      "accessibility": 4,
      "cumulative": 5
    },
    "lighthouse": {
      "version": "11.5.0",
      "performance": 0.72,
      "accessibility": 1,
      "bestPractices": 0.81,
      "seo": 0.91,
      "total": 344
    },
    "firstContentfulPaint": 2377.2565,
    "firstMeaningfulPaint": 2377.2565,
    "speedIndex": 2986.4685502740567,
    "largestContentfulPaint": 10094.0295,
    "totalBlockingTime": 33,
    "cumulativeLayoutShift": 0.01855206187032167,
    "timeToInteractive": 10466.813000000002,
    "maxPotentialFirstInputDelay": 106,
    "timeToFirstByte": 16.419999999999998,
    "weight": {
      "summary": "53 requests • 4,4 MiB",
      "total": 4628705,
      "image": 3903110,
      "imageCount": 10,
      "script": 203426,
      "scriptCount": 10,
      "document": 190491,
      "font": 208937,
      "fontCount": 14,
      "stylesheet": 57106,
      "stylesheetCount": 9,
      "thirdParty": 596438,
      "thirdPartyCount": 7
    },
    "run": {
      "number": 3,
      "total": 3
    },
    "sidequests": {
      "-weight.total": 39,
      "+weight.total": 9,
      "-weight.document": 7,
      "+weight.document": 41,
      "-weight.script": 28,
      "+weight.script": 7,
      "-weight.image": 34,
      "+weight.image": 9,
      "-weight.font": 8,
      "+weight.font": 32,
      "+weight.fontCount": 5,
      "-timeToFirstByte": 8,
      "-totalBlockingTime": 2,
      "-largestContentfulPaint": 40
    },
    "axe": {
      "passes": 613,
      "violations": 3
    }
  },
  {
    "url": "https://www.stellantis.com/fr/marques/ds",
    "requestedUrl": "https://www.stellantis.com/fr/marques/ds",
    "timestamp": 1707632721328,
    "ranks": {
      "hundos": 8,
      "performance": 25,
      "accessibility": 7,
      "cumulative": 6
    },
    "lighthouse": {
      "version": "11.5.0",
      "performance": 0.72,
      "accessibility": 1,
      "bestPractices": 0.81,
      "seo": 0.91,
      "total": 344
    },
    "firstContentfulPaint": 2571.239,
    "firstMeaningfulPaint": 2571.239,
    "speedIndex": 3393.3677340343647,
    "largestContentfulPaint": 6739.691,
    "totalBlockingTime": 61,
    "cumulativeLayoutShift": 0.006765610594248508,
    "timeToInteractive": 9116.5635,
    "maxPotentialFirstInputDelay": 106,
    "timeToFirstByte": 37.87,
    "weight": {
      "summary": "54 requests • 1,4 MiB",
      "total": 1415488,
      "image": 667185,
      "imageCount": 7,
      "script": 203422,
      "scriptCount": 10,
      "document": 189728,
      "font": 232378,
      "fontCount": 15,
      "stylesheet": 57076,
      "stylesheetCount": 9,
      "thirdParty": 621084,
      "thirdPartyCount": 8
    },
    "run": {
      "number": 1,
      "total": 3
    },
    "sidequests": {
      "-weight.total": 26,
      "+weight.total": 22,
      "-weight.document": 3,
      "+weight.document": 45,
      "-weight.script": 24,
      "+weight.script": 11,
      "-weight.image": 21,
      "+weight.image": 22,
      "-weight.font": 19,
      "+weight.font": 21,
      "+weight.fontCount": 4,
      "-timeToFirstByte": 25,
      "-totalBlockingTime": 19,
      "-largestContentfulPaint": 33
    },
    "axe": {
      "passes": 540,
      "violations": 3
    }
  },
  {
    "url": "https://www.stellantis.com/fr/actualite/communiques-de-presse/2023/juin/stellantis-adapte-son-equipe-de-direction-pour-renforcer-l-efficience-de-l-entreprise-dans-un-environnement-externe-de-plus-en-plus-exigeant",
    "requestedUrl": "https://www.stellantis.com/fr/actualite/communiques-de-presse/2023/juin/stellantis-adapte-son-equipe-de-direction-pour-renforcer-l-efficience-de-l-entreprise-dans-un-environnement-externe-de-plus-en-plus-exigeant",
    "timestamp": 1707633930773,
    "ranks": {
      "hundos": 6,
      "performance": 5,
      "accessibility": 25,
      "cumulative": 7
    },
    "lighthouse": {
      "version": "11.5.0",
      "performance": 0.74,
      "accessibility": 0.98,
      "bestPractices": 0.81,
      "seo": 0.91,
      "total": 344
    },
    "firstContentfulPaint": 2316.723,
    "firstMeaningfulPaint": 2316.723,
    "speedIndex": 2672.764375535733,
    "largestContentfulPaint": 6444.905000000001,
    "totalBlockingTime": 63,
    "cumulativeLayoutShift": 0.032142756252332205,
    "timeToInteractive": 7707.401000000002,
    "maxPotentialFirstInputDelay": 149,
    "timeToFirstByte": 34.66,
    "weight": {
      "summary": "56 requests • 1,1 MiB",
      "total": 1204458,
      "image": 440753,
      "imageCount": 8,
      "script": 203364,
      "scriptCount": 10,
      "document": 192730,
      "font": 244863,
      "fontCount": 16,
      "stylesheet": 57101,
      "stylesheetCount": 9,
      "thirdParty": 633486,
      "thirdPartyCount": 8
    },
    "run": {
      "number": 3,
      "total": 3
    },
    "sidequests": {
      "-weight.total": 17,
      "+weight.total": 31,
      "-weight.document": 23,
      "+weight.document": 25,
      "-weight.script": 10,
      "+weight.script": 25,
      "-weight.image": 7,
      "+weight.image": 36,
      "-weight.font": 28,
      "+weight.font": 12,
      "+weight.fontCount": 3,
      "-timeToFirstByte": 22,
      "-totalBlockingTime": 22,
      "-largestContentfulPaint": 24
    },
    "axe": {
      "passes": 690,
      "violations": 4
    }
  },
  {
    "url": "https://www.stellantis.com/fr/actualite/communiques-de-presse/2021/novembre/stellantis-annonce-le-lancement-de-stellantis-and-you-sales-and-services",
    "requestedUrl": "https://www.stellantis.com/fr/actualite/communiques-de-presse/2021/novembre/stellantis-annonce-le-lancement-de-stellantis-and-you-sales-and-services",
    "timestamp": 1707633056927,
    "ranks": {
      "hundos": 7,
      "performance": 14,
      "accessibility": 21,
      "cumulative": 8
    },
    "lighthouse": {
      "version": "11.5.0",
      "performance": 0.74,
      "accessibility": 0.98,
      "bestPractices": 0.81,
      "seo": 0.91,
      "total": 344
    },
    "firstContentfulPaint": 2326.0259999999994,
    "firstMeaningfulPaint": 2326.0259999999994,
    "speedIndex": 3636.8796575430692,
    "largestContentfulPaint": 6203.133,
    "totalBlockingTime": 39,
    "cumulativeLayoutShift": 0.008036228626461474,
    "timeToInteractive": 7657.232999999998,
    "maxPotentialFirstInputDelay": 107,
    "timeToFirstByte": 45.465,
    "weight": {
      "summary": "55 requests • 1,1 MiB",
      "total": 1185799,
      "image": 436090,
      "imageCount": 8,
      "script": 203308,
      "scriptCount": 10,
      "document": 192775,
      "font": 230828,
      "fontCount": 15,
      "stylesheet": 57100,
      "stylesheetCount": 9,
      "thirdParty": 619456,
      "thirdPartyCount": 8
    },
    "run": {
      "number": 1,
      "total": 3
    },
    "sidequests": {
      "-weight.total": 8,
      "+weight.total": 40,
      "-weight.document": 24,
      "+weight.document": 24,
      "-weight.script": 4,
      "+weight.script": 31,
      "-weight.image": 5,
      "+weight.image": 38,
      "-weight.font": 14,
      "+weight.font": 26,
      "+weight.fontCount": 4,
      "-timeToFirstByte": 39,
      "-totalBlockingTime": 6,
      "-largestContentfulPaint": 19
    },
    "axe": {
      "passes": 698,
      "violations": 4
    }
  },
  {
    "url": "https://www.stellantis.com/fr/actualite/communiques-de-presse/2023/july/sept-constructeurs-automobiles-s-associent-pour-creer-un-innovant-reseau-de-recharge-haute-puissance-en-amerique-du-nord",
    "requestedUrl": "https://www.stellantis.com/fr/actualite/communiques-de-presse/2023/july/sept-constructeurs-automobiles-s-associent-pour-creer-un-innovant-reseau-de-recharge-haute-puissance-en-amerique-du-nord",
    "timestamp": 1707632845967,
    "ranks": {
      "hundos": 9,
      "performance": 13,
      "accessibility": 16,
      "cumulative": 9
    },
    "lighthouse": {
      "version": "11.5.0",
      "performance": 0.74,
      "accessibility": 0.98,
      "bestPractices": 0.81,
      "seo": 0.91,
      "total": 344
    },
    "firstContentfulPaint": 2525.404,
    "firstMeaningfulPaint": 2525.404,
    "speedIndex": 3433.8613905275593,
    "largestContentfulPaint": 5937.719999999999,
    "totalBlockingTime": 91.5,
    "cumulativeLayoutShift": 0.009513650358059064,
    "timeToInteractive": 9109.43,
    "maxPotentialFirstInputDelay": 110,
    "timeToFirstByte": 42.138000000000005,
    "weight": {
      "summary": "56 requests • 2,5 MiB",
      "total": 2645500,
      "image": 1879719,
      "imageCount": 8,
      "script": 203424,
      "scriptCount": 10,
      "document": 194701,
      "font": 244856,
      "fontCount": 16,
      "stylesheet": 57106,
      "stylesheetCount": 9,
      "thirdParty": 633582,
      "thirdPartyCount": 8
    },
    "run": {
      "number": 1,
      "total": 3
    },
    "sidequests": {
      "-weight.total": 34,
      "+weight.total": 14,
      "-weight.document": 36,
      "+weight.document": 12,
      "-weight.script": 26,
      "+weight.script": 9,
      "-weight.image": 29,
      "+weight.image": 14,
      "-weight.font": 24,
      "+weight.font": 16,
      "+weight.fontCount": 3,
      "-timeToFirstByte": 32,
      "-totalBlockingTime": 32,
      "-largestContentfulPaint": 7
    },
    "axe": {
      "passes": 719,
      "violations": 4
    }
  },
  {
    "url": "https://www.stellantis.com/fr/actualite/evenements-presse",
    "requestedUrl": "https://www.stellantis.com/fr/actualite/evenements-presse",
    "timestamp": 1707633150477,
    "ranks": {
      "hundos": 12,
      "performance": 28,
      "accessibility": 2,
      "cumulative": 10
    },
    "lighthouse": {
      "version": "11.5.0",
      "performance": 0.71,
      "accessibility": 1,
      "bestPractices": 0.81,
      "seo": 0.91,
      "total": 343
    },
    "firstContentfulPaint": 2356.2495,
    "firstMeaningfulPaint": 2356.2495,
    "speedIndex": 2635.970929438816,
    "largestContentfulPaint": 18741.2245,
    "totalBlockingTime": 67,
    "cumulativeLayoutShift": 0.061438940959475795,
    "timeToInteractive": 7110.113499999998,
    "maxPotentialFirstInputDelay": 148,
    "timeToFirstByte": 43.75,
    "weight": {
      "summary": "58 requests • 5,6 MiB",
      "total": 5829542,
      "image": 5119592,
      "imageCount": 17,
      "script": 203358,
      "scriptCount": 10,
      "document": 191415,
      "font": 193629,
      "fontCount": 13,
      "stylesheet": 57103,
      "stylesheetCount": 9,
      "thirdParty": 581049,
      "thirdPartyCount": 7
    },
    "run": {
      "number": 1,
      "total": 3
    },
    "sidequests": {
      "-weight.total": 43,
      "+weight.total": 5,
      "-weight.document": 12,
      "+weight.document": 36,
      "-weight.script": 9,
      "+weight.script": 26,
      "-weight.image": 38,
      "+weight.image": 5,
      "-weight.font": 3,
      "+weight.font": 37,
      "+weight.fontCount": 6,
      "-timeToFirstByte": 37,
      "-totalBlockingTime": 26,
      "-largestContentfulPaint": 45
    },
    "axe": {
      "passes": 757,
      "violations": 3
    }
  },
  {
    "url": "https://www.stellantis.com/fr/technologie/pile-a-combustible-a-hydrogene",
    "requestedUrl": "https://www.stellantis.com/fr/technologie/pile-a-combustible-a-hydrogene",
    "timestamp": 1707632711142,
    "ranks": {
      "hundos": 17,
      "performance": 31,
      "accessibility": 3,
      "cumulative": 11
    },
    "lighthouse": {
      "version": "11.5.0",
      "performance": 0.71,
      "accessibility": 1,
      "bestPractices": 0.81,
      "seo": 0.91,
      "total": 343
    },
    "firstContentfulPaint": 2471.8540000000003,
    "firstMeaningfulPaint": 2471.8540000000003,
    "speedIndex": 3678.12949931154,
    "largestContentfulPaint": 9176.23,
    "totalBlockingTime": 64.00000000000091,
    "cumulativeLayoutShift": 0.0137961616170897,
    "timeToInteractive": 10049.5195,
    "maxPotentialFirstInputDelay": 106,
    "timeToFirstByte": 15.363,
    "weight": {
      "summary": "49 requests • 2,0 MiB",
      "total": 2051574,
      "image": 1351285,
      "imageCount": 9,
      "script": 203427,
      "scriptCount": 10,
      "document": 192579,
      "font": 182750,
      "fontCount": 12,
      "stylesheet": 57060,
      "stylesheetCount": 9,
      "thirdParty": 570210,
      "thirdPartyCount": 7
    },
    "run": {
      "number": 1,
      "total": 3
    },
    "sidequests": {
      "-weight.total": 32,
      "+weight.total": 16,
      "-weight.document": 22,
      "+weight.document": 26,
      "-weight.script": 29,
      "+weight.script": 6,
      "-weight.image": 28,
      "+weight.image": 15,
      "-weight.font": 2,
      "+weight.font": 38,
      "+weight.fontCount": 7,
      "-timeToFirstByte": 2,
      "-totalBlockingTime": 24,
      "-largestContentfulPaint": 39
    },
    "axe": {
      "passes": 702,
      "violations": 3
    }
  },
  {
    "url": "https://www.stellantis.com/fr/actualite/communiques-de-presse/2023/janvier/la-nouvelle-business-unit-mobilisights-developpera-l-offre-croissante-de-data-et-services-connectes-de-stellantis",
    "requestedUrl": "https://www.stellantis.com/fr/actualite/communiques-de-presse/2023/janvier/la-nouvelle-business-unit-mobilisights-developpera-l-offre-croissante-de-data-et-services-connectes-de-stellantis",
    "timestamp": 1707633991833,
    "ranks": {
      "hundos": 10,
      "performance": 16,
      "accessibility": 14,
      "cumulative": 12
    },
    "lighthouse": {
      "version": "11.5.0",
      "performance": 0.73,
      "accessibility": 0.98,
      "bestPractices": 0.81,
      "seo": 0.91,
      "total": 343
    },
    "firstContentfulPaint": 2479.4105,
    "firstMeaningfulPaint": 2479.4105,
    "speedIndex": 2771.3688911237505,
    "largestContentfulPaint": 6673.5725,
    "totalBlockingTime": 34.5,
    "cumulativeLayoutShift": 0.054387281706627,
    "timeToInteractive": 9581.077,
    "maxPotentialFirstInputDelay": 109,
    "timeToFirstByte": 36.57199999999999,
    "weight": {
      "summary": "57 requests • 1,5 MiB",
      "total": 1592801,
      "image": 825530,
      "imageCount": 9,
      "script": 203417,
      "scriptCount": 10,
      "document": 194486,
      "font": 246533,
      "fontCount": 16,
      "stylesheet": 57101,
      "stylesheetCount": 9,
      "thirdParty": 635297,
      "thirdPartyCount": 8
    },
    "run": {
      "number": 3,
      "total": 3
    },
    "sidequests": {
      "-weight.total": 28,
      "+weight.total": 20,
      "-weight.document": 33,
      "+weight.document": 15,
      "-weight.script": 21,
      "+weight.script": 14,
      "-weight.image": 24,
      "+weight.image": 19,
      "-weight.font": 30,
      "+weight.font": 10,
      "+weight.fontCount": 3,
      "-timeToFirstByte": 23,
      "-totalBlockingTime": 3,
      "-largestContentfulPaint": 32
    },
    "axe": {
      "passes": 729,
      "violations": 4
    }
  },
  {
    "url": "https://www.stellantis.com/fr/actualite/communiques-de-presse/2021/mars/stellantis-publie-l-ordre-du-jour-de-l-aga-2021",
    "requestedUrl": "https://www.stellantis.com/fr/actualite/communiques-de-presse/2021/mars/stellantis-publie-l-ordre-du-jour-de-l-aga-2021",
    "timestamp": 1707633107904,
    "ranks": {
      "hundos": 11,
      "performance": 6,
      "accessibility": 29,
      "cumulative": 13
    },
    "lighthouse": {
      "version": "11.5.0",
      "performance": 0.74,
      "accessibility": 0.98,
      "bestPractices": 0.81,
      "seo": 0.9,
      "total": 343
    },
    "firstContentfulPaint": 2351.147,
    "firstMeaningfulPaint": 2351.147,
    "speedIndex": 2768.540315767872,
    "largestContentfulPaint": 6531.362,
    "totalBlockingTime": 54.5,
    "cumulativeLayoutShift": 0.05666035446402286,
    "timeToInteractive": 7755.5210000000025,
    "maxPotentialFirstInputDelay": 147,
    "timeToFirstByte": 46.437,
    "weight": {
      "summary": "56 requests • 1,1 MiB",
      "total": 1203359,
      "image": 440751,
      "imageCount": 8,
      "script": 203318,
      "scriptCount": 10,
      "document": 191679,
      "font": 244863,
      "fontCount": 16,
      "stylesheet": 57101,
      "stylesheetCount": 9,
      "thirdParty": 633441,
      "thirdPartyCount": 8
    },
    "run": {
      "number": 1,
      "total": 3
    },
    "sidequests": {
      "-weight.total": 15,
      "+weight.total": 33,
      "-weight.document": 16,
      "+weight.document": 32,
      "-weight.script": 6,
      "+weight.script": 29,
      "-weight.image": 6,
      "+weight.image": 37,
      "-weight.font": 28,
      "+weight.font": 12,
      "+weight.fontCount": 3,
      "-timeToFirstByte": 40,
      "-totalBlockingTime": 13,
      "-largestContentfulPaint": 27
    },
    "axe": {
      "passes": 688,
      "violations": 4
    }
  },
  {
    "url": "https://www.stellantis.com/fr/actualite/communiques-de-presse/2021/septembre/changements-dans-l-equipe-dirigeante",
    "requestedUrl": "https://www.stellantis.com/fr/actualite/communiques-de-presse/2021/septembre/changements-dans-l-equipe-dirigeante",
    "timestamp": 1707633598432,
    "ranks": {
      "hundos": 13,
      "performance": 12,
      "accessibility": 27,
      "cumulative": 14
    },
    "lighthouse": {
      "version": "11.5.0",
      "performance": 0.74,
      "accessibility": 0.98,
      "bestPractices": 0.81,
      "seo": 0.9,
      "total": 343
    },
    "firstContentfulPaint": 2383.368,
    "firstMeaningfulPaint": 2383.368,
    "speedIndex": 3425.9323460138467,
    "largestContentfulPaint": 6374.388000000001,
    "totalBlockingTime": 39.5,
    "cumulativeLayoutShift": 0.01750198491685366,
    "timeToInteractive": 7654.8330000000005,
    "maxPotentialFirstInputDelay": 108,
    "timeToFirstByte": 33.867999999999995,
    "weight": {
      "summary": "54 requests • 1,1 MiB",
      "total": 1167058,
      "image": 417985,
      "imageCount": 7,
      "script": 203415,
      "scriptCount": 10,
      "document": 192034,
      "font": 230828,
      "fontCount": 15,
      "stylesheet": 57101,
      "stylesheetCount": 9,
      "thirdParty": 619556,
      "thirdPartyCount": 8
    },
    "run": {
      "number": 2,
      "total": 3
    },
    "sidequests": {
      "-weight.total": 6,
      "+weight.total": 42,
      "-weight.document": 19,
      "+weight.document": 29,
      "-weight.script": 19,
      "+weight.script": 16,
      "-weight.image": 4,
      "+weight.image": 39,
      "-weight.font": 14,
      "+weight.font": 26,
      "+weight.fontCount": 4,
      "-timeToFirstByte": 20,
      "-totalBlockingTime": 7,
      "-largestContentfulPaint": 23
    },
    "axe": {
      "passes": 688,
      "violations": 4
    }
  },
  {
    "url": "https://www.stellantis.com/fr/finance/informations-obligations",
    "requestedUrl": "https://www.stellantis.com/fr/finance/informations-obligations",
    "timestamp": 1707632784381,
    "ranks": {
      "hundos": 14,
      "performance": 2,
      "accessibility": 34,
      "cumulative": 15
    },
    "lighthouse": {
      "version": "11.5.0",
      "performance": 0.75,
      "accessibility": 0.96,
      "bestPractices": 0.81,
      "seo": 0.91,
      "total": 343
    },
    "firstContentfulPaint": 2395.2429999999995,
    "firstMeaningfulPaint": 2395.2429999999995,
    "speedIndex": 2805.869948751576,
    "largestContentfulPaint": 5946.887,
    "totalBlockingTime": 63.5,
    "cumulativeLayoutShift": 0.005430431464756761,
    "timeToInteractive": 8672.043000000001,
    "maxPotentialFirstInputDelay": 149,
    "timeToFirstByte": 48.935,
    "weight": {
      "summary": "49 requests • 1,1 MiB",
      "total": 1172059,
      "image": 414354,
      "imageCount": 3,
      "script": 203410,
      "scriptCount": 10,
      "document": 211154,
      "font": 220379,
      "fontCount": 14,
      "stylesheet": 57056,
      "stylesheetCount": 9,
      "thirdParty": 609069,
      "thirdPartyCount": 8
    },
    "run": {
      "number": 1,
      "total": 3
    },
    "sidequests": {
      "-weight.total": 7,
      "+weight.total": 41,
      "-weight.document": 43,
      "+weight.document": 5,
      "-weight.script": 15,
      "+weight.script": 20,
      "-weight.image": 3,
      "+weight.image": 40,
      "-weight.font": 12,
      "+weight.font": 28,
      "+weight.fontCount": 5,
      "-timeToFirstByte": 41,
      "-totalBlockingTime": 23,
      "-largestContentfulPaint": 8
    },
    "axe": {
      "passes": 1170,
      "violations": 4
    }
  },
  {
    "url": "https://www.stellantis.com/fr/actualite/communiques-de-presse/2021/avril/publication-du-chiffre-d-affaires-du-premier-trimestre-2021-le-mercredi-5-mai",
    "requestedUrl": "https://www.stellantis.com/fr/actualite/communiques-de-presse/2021/avril/publication-du-chiffre-d-affaires-du-premier-trimestre-2021-le-mercredi-5-mai",
    "timestamp": 1707634159041,
    "ranks": {
      "hundos": 15,
      "performance": 8,
      "accessibility": 24,
      "cumulative": 16
    },
    "lighthouse": {
      "version": "11.5.0",
      "performance": 0.74,
      "accessibility": 0.98,
      "bestPractices": 0.81,
      "seo": 0.9,
      "total": 343
    },
    "firstContentfulPaint": 2363.496,
    "firstMeaningfulPaint": 2363.496,
    "speedIndex": 3285.1095641132674,
    "largestContentfulPaint": 5980.588000000001,
    "totalBlockingTime": 77.5,
    "cumulativeLayoutShift": 0.051873249401414495,
    "timeToInteractive": 8537.603500000001,
    "maxPotentialFirstInputDelay": 108,
    "timeToFirstByte": 15.808000000000007,
    "weight": {
      "summary": "52 requests • 1,1 MiB",
      "total": 1202083,
      "image": 440755,
      "imageCount": 8,
      "script": 203423,
      "scriptCount": 10,
      "document": 191484,
      "font": 244854,
      "fontCount": 16,
      "stylesheet": 57102,
      "stylesheetCount": 9,
      "thirdParty": 632352,
      "thirdPartyCount": 7
    },
    "run": {
      "number": 3,
      "total": 3
    },
    "sidequests": {
      "-weight.total": 11,
      "+weight.total": 37,
      "-weight.document": 14,
      "+weight.document": 34,
      "-weight.script": 25,
      "+weight.script": 10,
      "-weight.image": 8,
      "+weight.image": 35,
      "-weight.font": 22,
      "+weight.font": 18,
      "+weight.fontCount": 3,
      "-timeToFirstByte": 6,
      "-totalBlockingTime": 31,
      "-largestContentfulPaint": 12
    },
    "axe": {
      "passes": 691,
      "violations": 4
    }
  },
  {
    "url": "https://www.stellantis.com/fr/actualite/communiques-de-presse/2022/mai/stellantis-et-toyota-elargissent-leur-partenariat-avec-un-nouveau-fourgon-grand-volume-egalement-disponible-en-version-electrique",
    "requestedUrl": "https://www.stellantis.com/fr/actualite/communiques-de-presse/2022/mai/stellantis-et-toyota-elargissent-leur-partenariat-avec-un-nouveau-fourgon-grand-volume-egalement-disponible-en-version-electrique",
    "timestamp": 1707632992802,
    "ranks": {
      "hundos": 16,
      "performance": 17,
      "accessibility": 15,
      "cumulative": 17
    },
    "lighthouse": {
      "version": "11.5.0",
      "performance": 0.73,
      "accessibility": 0.98,
      "bestPractices": 0.81,
      "seo": 0.91,
      "total": 343
    },
    "firstContentfulPaint": 2794.334,
    "firstMeaningfulPaint": 2794.334,
    "speedIndex": 3249.9472629570546,
    "largestContentfulPaint": 5973.751,
    "totalBlockingTime": 55.5,
    "cumulativeLayoutShift": 0.0014842675486953772,
    "timeToInteractive": 8478.0645,
    "maxPotentialFirstInputDelay": 148,
    "timeToFirstByte": 40.95099999999999,
    "weight": {
      "summary": "52 requests • 1,2 MiB",
      "total": 1206705,
      "image": 440942,
      "imageCount": 8,
      "script": 203372,
      "scriptCount": 10,
      "document": 196035,
      "font": 244855,
      "fontCount": 16,
      "stylesheet": 57081,
      "stylesheetCount": 9,
      "thirdParty": 632235,
      "thirdPartyCount": 7
    },
    "run": {
      "number": 1,
      "total": 3
    },
    "sidequests": {
      "-weight.total": 18,
      "+weight.total": 30,
      "-weight.document": 39,
      "+weight.document": 9,
      "-weight.script": 12,
      "+weight.script": 23,
      "-weight.image": 14,
      "+weight.image": 29,
      "-weight.font": 23,
      "+weight.font": 17,
      "+weight.fontCount": 3,
      "-timeToFirstByte": 30,
      "-totalBlockingTime": 14,
      "-largestContentfulPaint": 10
    },
    "axe": {
      "passes": 723,
      "violations": 4
    }
  },
  {
    "url": "https://www.stellantis.com/fr/finance/reporting/autres-informations-reglementaires",
    "requestedUrl": "https://www.stellantis.com/fr/finance/reporting/autres-informations-reglementaires",
    "timestamp": 1707633838248,
    "ranks": {
      "hundos": 19,
      "performance": 36,
      "accessibility": 1,
      "cumulative": 18
    },
    "lighthouse": {
      "version": "11.5.0",
      "performance": 0.69,
      "accessibility": 1,
      "bestPractices": 0.81,
      "seo": 0.92,
      "total": 342
    },
    "firstContentfulPaint": 2330.8015,
    "firstMeaningfulPaint": 2330.8015,
    "speedIndex": 3132.0798374007504,
    "largestContentfulPaint": 5850.0475,
    "totalBlockingTime": 72,
    "cumulativeLayoutShift": 0.1506164659388397,
    "timeToInteractive": 8781.976999999999,
    "maxPotentialFirstInputDelay": 108,
    "timeToFirstByte": 16.839000000000006,
    "weight": {
      "summary": "48 requests • 1,1 MiB",
      "total": 1126180,
      "image": 414347,
      "imageCount": 3,
      "script": 203422,
      "scriptCount": 10,
      "document": 190140,
      "font": 195468,
      "fontCount": 13,
      "stylesheet": 57099,
      "stylesheetCount": 9,
      "thirdParty": 584204,
      "thirdPartyCount": 8
    },
    "run": {
      "number": 3,
      "total": 3
    },
    "sidequests": {
      "-weight.total": 3,
      "+weight.total": 45,
      "-weight.document": 6,
      "+weight.document": 42,
      "-weight.script": 24,
      "+weight.script": 11,
      "-weight.image": 1,
      "+weight.image": 42,
      "-weight.font": 5,
      "+weight.font": 35,
      "+weight.fontCount": 6,
      "-timeToFirstByte": 9,
      "-totalBlockingTime": 29,
      "-largestContentfulPaint": 5
    },
    "axe": {
      "passes": 951,
      "violations": 3
    }
  },
  {
    "url": "https://www.stellantis.com/fr/actualite/communiques-de-presse/2023/fevrier/stellantis-annonce-des-changements-de-symboles-boursiers-sur-euronext",
    "requestedUrl": "https://www.stellantis.com/fr/actualite/communiques-de-presse/2023/fevrier/stellantis-annonce-des-changements-de-symboles-boursiers-sur-euronext",
    "timestamp": 1707632918858,
    "ranks": {
      "hundos": 18,
      "performance": 20,
      "accessibility": 33,
      "cumulative": 19
    },
    "lighthouse": {
      "version": "11.5.0",
      "performance": 0.72,
      "accessibility": 0.98,
      "bestPractices": 0.81,
      "seo": 0.91,
      "total": 342
    },
    "firstContentfulPaint": 2648.534,
    "firstMeaningfulPaint": 2648.534,
    "speedIndex": 2917.5013722795716,
    "largestContentfulPaint": 6589.503999999999,
    "totalBlockingTime": 38,
    "cumulativeLayoutShift": 0.048083396769316056,
    "timeToInteractive": 7753.569000000001,
    "maxPotentialFirstInputDelay": 106,
    "timeToFirstByte": 42.348000000000006,
    "weight": {
      "summary": "56 requests • 1,1 MiB",
      "total": 1203084,
      "image": 440758,
      "imageCount": 8,
      "script": 203413,
      "scriptCount": 10,
      "document": 191351,
      "font": 244862,
      "fontCount": 16,
      "stylesheet": 57051,
      "stylesheetCount": 9,
      "thirdParty": 633500,
      "thirdPartyCount": 8
    },
    "run": {
      "number": 1,
      "total": 3
    },
    "sidequests": {
      "-weight.total": 14,
      "+weight.total": 34,
      "-weight.document": 11,
      "+weight.document": 37,
      "-weight.script": 17,
      "+weight.script": 18,
      "-weight.image": 10,
      "+weight.image": 33,
      "-weight.font": 27,
      "+weight.font": 13,
      "+weight.fontCount": 3,
      "-timeToFirstByte": 33,
      "-totalBlockingTime": 4,
      "-largestContentfulPaint": 29
    },
    "axe": {
      "passes": 670,
      "violations": 4
    }
  },
  {
    "url": "https://www.stellantis.com/fr/actualite/communiques-de-presse/2022/septembre/chief-purchasing-and-supply-chain-officer-de-stellantis-participe-a-la-conference-bank-of-america-autos-and-future-car-conference-2022",
    "requestedUrl": "https://www.stellantis.com/fr/actualite/communiques-de-presse/2022/septembre/chief-purchasing-and-supply-chain-officer-de-stellantis-participe-a-la-conference-bank-of-america-autos-and-future-car-conference-2022",
    "timestamp": 1707634023153,
    "ranks": {
      "hundos": 20,
      "performance": 26,
      "accessibility": 30,
      "cumulative": 20
    },
    "lighthouse": {
      "version": "11.5.0",
      "performance": 0.72,
      "accessibility": 0.98,
      "bestPractices": 0.81,
      "seo": 0.91,
      "total": 342
    },
    "firstContentfulPaint": 2377.677,
    "firstMeaningfulPaint": 2377.677,
    "speedIndex": 3412.9365232877176,
    "largestContentfulPaint": 6467.036000000001,
    "totalBlockingTime": 64.5,
    "cumulativeLayoutShift": 0.08323677389458109,
    "timeToInteractive": 7660.262000000001,
    "maxPotentialFirstInputDelay": 151,
    "timeToFirstByte": 22.800999999999995,
    "weight": {
      "summary": "55 requests • 1,1 MiB",
      "total": 1188864,
      "image": 440771,
      "imageCount": 8,
      "script": 203419,
      "scriptCount": 10,
      "document": 191070,
      "font": 230829,
      "fontCount": 15,
      "stylesheet": 57080,
      "stylesheetCount": 9,
      "thirdParty": 619534,
      "thirdPartyCount": 8
    },
    "run": {
      "number": 3,
      "total": 3
    },
    "sidequests": {
      "-weight.total": 9,
      "+weight.total": 39,
      "-weight.document": 9,
      "+weight.document": 39,
      "-weight.script": 22,
      "+weight.script": 13,
      "-weight.image": 13,
      "+weight.image": 30,
      "-weight.font": 15,
      "+weight.font": 25,
      "+weight.fontCount": 4,
      "-timeToFirstByte": 16,
      "-totalBlockingTime": 25,
      "-largestContentfulPaint": 25
    },
    "axe": {
      "passes": 684,
      "violations": 4
    }
  },
  {
    "url": "https://www.stellantis.com/fr/actualite/communiques-de-presse/2022/decembre/stellantis-et-qinomic-s-associent-pour-developper-le-retrofit-electrique-des-vehicules-utilitaires-legers",
    "requestedUrl": "https://www.stellantis.com/fr/actualite/communiques-de-presse/2022/decembre/stellantis-et-qinomic-s-associent-pour-developper-le-retrofit-electrique-des-vehicules-utilitaires-legers",
    "timestamp": 1707633470410,
    "ranks": {
      "hundos": 21,
      "performance": 27,
      "accessibility": 18,
      "cumulative": 21
    },
    "lighthouse": {
      "version": "11.5.0",
      "performance": 0.72,
      "accessibility": 0.98,
      "bestPractices": 0.81,
      "seo": 0.91,
      "total": 342
    },
    "firstContentfulPaint": 2797.6170000000006,
    "firstMeaningfulPaint": 2797.6170000000006,
    "speedIndex": 3456.175864165335,
    "largestContentfulPaint": 6129.023,
    "totalBlockingTime": 118.49999999999955,
    "cumulativeLayoutShift": 0.007575523473040242,
    "timeToInteractive": 8789.937999999998,
    "maxPotentialFirstInputDelay": 146,
    "timeToFirstByte": 16.323000000000008,
    "weight": {
      "summary": "52 requests • 1,2 MiB",
      "total": 1242007,
      "image": 478949,
      "imageCount": 8,
      "script": 203427,
      "scriptCount": 10,
      "document": 193178,
      "font": 244879,
      "fontCount": 16,
      "stylesheet": 57107,
      "stylesheetCount": 9,
      "thirdParty": 632380,
      "thirdPartyCount": 7
    },
    "run": {
      "number": 2,
      "total": 3
    },
    "sidequests": {
      "-weight.total": 22,
      "+weight.total": 26,
      "-weight.document": 28,
      "+weight.document": 20,
      "-weight.script": 29,
      "+weight.script": 6,
      "-weight.image": 17,
      "+weight.image": 26,
      "-weight.font": 29,
      "+weight.font": 11,
      "+weight.fontCount": 3,
      "-timeToFirstByte": 7,
      "-totalBlockingTime": 34,
      "-largestContentfulPaint": 17
    },
    "axe": {
      "passes": 715,
      "violations": 4
    }
  },
  {
    "url": "https://www.stellantis.com/fr/actualite/communiques-de-presse/2021/janvier/nouvelle-denomination-et-nouvelle-gouvernance-de-stellantis",
    "requestedUrl": "https://www.stellantis.com/fr/actualite/communiques-de-presse/2021/janvier/nouvelle-denomination-et-nouvelle-gouvernance-de-stellantis",
    "timestamp": 1707634189394,
    "ranks": {
      "hundos": 22,
      "performance": 19,
      "accessibility": 23,
      "cumulative": 22
    },
    "lighthouse": {
      "version": "11.5.0",
      "performance": 0.72,
      "accessibility": 0.98,
      "bestPractices": 0.81,
      "seo": 0.9,
      "total": 341
    },
    "firstContentfulPaint": 2513.7470000000003,
    "firstMeaningfulPaint": 2513.7470000000003,
    "speedIndex": 2819.1600401331234,
    "largestContentfulPaint": 6602.378000000001,
    "totalBlockingTime": 38.5,
    "cumulativeLayoutShift": 0.07148254865929188,
    "timeToInteractive": 7244.206,
    "maxPotentialFirstInputDelay": 107,
    "timeToFirstByte": 19.064,
    "weight": {
      "summary": "53 requests • 1,2 MiB",
      "total": 1212192,
      "image": 444039,
      "imageCount": 8,
      "script": 203356,
      "scriptCount": 10,
      "document": 193754,
      "font": 249517,
      "fontCount": 17,
      "stylesheet": 57103,
      "stylesheetCount": 9,
      "thirdParty": 636913,
      "thirdPartyCount": 7
    },
    "run": {
      "number": 3,
      "total": 3
    },
    "sidequests": {
      "-weight.total": 20,
      "+weight.total": 28,
      "-weight.document": 30,
      "+weight.document": 18,
      "-weight.script": 7,
      "+weight.script": 28,
      "-weight.image": 15,
      "+weight.image": 28,
      "-weight.font": 35,
      "+weight.font": 5,
      "+weight.fontCount": 2,
      "-timeToFirstByte": 15,
      "-totalBlockingTime": 5,
      "-largestContentfulPaint": 30
    },
    "axe": {
      "passes": 695,
      "violations": 4
    }
  },
  {
    "url": "https://www.stellantis.com/fr/actualite/communiques-de-presse/2023/avril/stellantis-en-route-pour-atteindre-ses-objectifs-environnementaux-et-sociaux-ambitieux",
    "requestedUrl": "https://www.stellantis.com/fr/actualite/communiques-de-presse/2023/avril/stellantis-en-route-pour-atteindre-ses-objectifs-environnementaux-et-sociaux-ambitieux",
    "timestamp": 1707633941018,
    "ranks": {
      "hundos": 23,
      "performance": 29,
      "accessibility": 13,
      "cumulative": 23
    },
    "lighthouse": {
      "version": "11.5.0",
      "performance": 0.71,
      "accessibility": 0.98,
      "bestPractices": 0.81,
      "seo": 0.91,
      "total": 341
    },
    "firstContentfulPaint": 2343.9629999999997,
    "firstMeaningfulPaint": 2343.9629999999997,
    "speedIndex": 3204.9922522313864,
    "largestContentfulPaint": 10423.468,
    "totalBlockingTime": 59.5,
    "cumulativeLayoutShift": 0.06912845024075291,
    "timeToInteractive": 7699.387999999999,
    "maxPotentialFirstInputDelay": 146,
    "timeToFirstByte": 17.241,
    "weight": {
      "summary": "55 requests • 1,9 MiB",
      "total": 1976885,
      "image": 1226769,
      "imageCount": 8,
      "script": 203422,
      "scriptCount": 10,
      "document": 193107,
      "font": 230837,
      "fontCount": 15,
      "stylesheet": 57101,
      "stylesheetCount": 9,
      "thirdParty": 619516,
      "thirdPartyCount": 8
    },
    "run": {
      "number": 3,
      "total": 3
    },
    "sidequests": {
      "-weight.total": 30,
      "+weight.total": 18,
      "-weight.document": 27,
      "+weight.document": 21,
      "-weight.script": 24,
      "+weight.script": 11,
      "-weight.image": 26,
      "+weight.image": 17,
      "-weight.font": 16,
      "+weight.font": 24,
      "+weight.fontCount": 4,
      "-timeToFirstByte": 11,
      "-totalBlockingTime": 17,
      "-largestContentfulPaint": 41
    },
    "axe": {
      "passes": 730,
      "violations": 4
    }
  },
  {
    "url": "https://www.stellantis.com/fr/actualite/communiques-de-presse/2023/octobre/stellantis-presentera-sa-strategie-et-sa-nouvelle-gamme-mondiale-de-vehicules-utilitaires-le-23-octobre-2023",
    "requestedUrl": "https://www.stellantis.com/fr/actualite/communiques-de-presse/2023/octobre/stellantis-presentera-sa-strategie-et-sa-nouvelle-gamme-mondiale-de-vehicules-utilitaires-le-23-octobre-2023",
    "timestamp": 1707633366151,
    "ranks": {
      "hundos": 24,
      "performance": 30,
      "accessibility": 32,
      "cumulative": 24
    },
    "lighthouse": {
      "version": "11.5.0",
      "performance": 0.71,
      "accessibility": 0.98,
      "bestPractices": 0.81,
      "seo": 0.91,
      "total": 341
    },
    "firstContentfulPaint": 2344.09,
    "firstMeaningfulPaint": 2344.09,
    "speedIndex": 3365.9992301701373,
    "largestContentfulPaint": 8126.040000000001,
    "totalBlockingTime": 61.999999999999545,
    "cumulativeLayoutShift": 0.06985216041595538,
    "timeToInteractive": 7769.6775,
    "maxPotentialFirstInputDelay": 146,
    "timeToFirstByte": 39.41100000000001,
    "weight": {
      "summary": "55 requests • 1,6 MiB",
      "total": 1665732,
      "image": 918109,
      "imageCount": 8,
      "script": 203411,
      "scriptCount": 10,
      "document": 190682,
      "font": 230691,
      "fontCount": 15,
      "stylesheet": 57105,
      "stylesheetCount": 9,
      "thirdParty": 619455,
      "thirdPartyCount": 8
    },
    "run": {
      "number": 2,
      "total": 3
    },
    "sidequests": {
      "-weight.total": 29,
      "+weight.total": 19,
      "-weight.document": 8,
      "+weight.document": 40,
      "-weight.script": 16,
      "+weight.script": 19,
      "-weight.image": 25,
      "+weight.image": 18,
      "-weight.font": 13,
      "+weight.font": 27,
      "+weight.fontCount": 4,
      "-timeToFirstByte": 27,
      "-totalBlockingTime": 20,
      "-largestContentfulPaint": 37
    },
    "axe": {
      "passes": 678,
      "violations": 4
    }
  },
  {
    "url": "https://www.stellantis.com/fr/actualite/communiques-de-presse/2021/february/calendrier-de-publication-financiere-2021",
    "requestedUrl": "https://www.stellantis.com/fr/actualite/communiques-de-presse/2021/february/calendrier-de-publication-financiere-2021",
    "timestamp": 1707634179262,
    "ranks": {
      "hundos": 25,
      "performance": 24,
      "accessibility": 20,
      "cumulative": 25
    },
    "lighthouse": {
      "version": "11.5.0",
      "performance": 0.72,
      "accessibility": 0.98,
      "bestPractices": 0.81,
      "seo": 0.9,
      "total": 341
    },
    "firstContentfulPaint": 2388.784999999999,
    "firstMeaningfulPaint": 2388.784999999999,
    "speedIndex": 3214.7971935157025,
    "largestContentfulPaint": 6322.077000000001,
    "totalBlockingTime": 40,
    "cumulativeLayoutShift": 0.0958807952725022,
    "timeToInteractive": 7271.377,
    "maxPotentialFirstInputDelay": 107,
    "timeToFirstByte": 89.644,
    "weight": {
      "summary": "52 requests • 1,1 MiB",
      "total": 1202099,
      "image": 440765,
      "imageCount": 8,
      "script": 203414,
      "scriptCount": 10,
      "document": 191523,
      "font": 244853,
      "fontCount": 16,
      "stylesheet": 57078,
      "stylesheetCount": 9,
      "thirdParty": 632327,
      "thirdPartyCount": 7
    },
    "run": {
      "number": 3,
      "total": 3
    },
    "sidequests": {
      "-weight.total": 12,
      "+weight.total": 36,
      "-weight.document": 15,
      "+weight.document": 33,
      "-weight.script": 18,
      "+weight.script": 17,
      "-weight.image": 11,
      "+weight.image": 32,
      "-weight.font": 21,
      "+weight.font": 19,
      "+weight.fontCount": 3,
      "-timeToFirstByte": 47,
      "-totalBlockingTime": 8,
      "-largestContentfulPaint": 20
    },
    "axe": {
      "passes": 700,
      "violations": 4
    }
  },
  {
    "url": "https://www.stellantis.com/fr/actualite/communiques-de-presse/2022/avril/stellantis-publiera-le-5-mai-2022-ses-resultats-du-1er-trimestre-2022",
    "requestedUrl": "https://www.stellantis.com/fr/actualite/communiques-de-presse/2022/avril/stellantis-publiera-le-5-mai-2022-ses-resultats-du-1er-trimestre-2022",
    "timestamp": 1707634064668,
    "ranks": {
      "hundos": 26,
      "performance": 33,
      "accessibility": 26,
      "cumulative": 26
    },
    "lighthouse": {
      "version": "11.5.0",
      "performance": 0.7,
      "accessibility": 0.98,
      "bestPractices": 0.81,
      "seo": 0.91,
      "total": 340
    },
    "firstContentfulPaint": 2325.143,
    "firstMeaningfulPaint": 2325.143,
    "speedIndex": 2909.6638991008163,
    "largestContentfulPaint": 6126.217,
    "totalBlockingTime": 39,
    "cumulativeLayoutShift": 0.1276937675211708,
    "timeToInteractive": 7751.8369999999995,
    "maxPotentialFirstInputDelay": 107,
    "timeToFirstByte": 15.782000000000004,
    "weight": {
      "summary": "55 requests • 1,1 MiB",
      "total": 1189077,
      "image": 440756,
      "imageCount": 8,
      "script": 203422,
      "scriptCount": 10,
      "document": 191336,
      "font": 230838,
      "fontCount": 15,
      "stylesheet": 57101,
      "stylesheetCount": 9,
      "thirdParty": 619493,
      "thirdPartyCount": 8
    },
    "run": {
      "number": 3,
      "total": 3
    },
    "sidequests": {
      "-weight.total": 10,
      "+weight.total": 38,
      "-weight.document": 10,
      "+weight.document": 38,
      "-weight.script": 24,
      "+weight.script": 11,
      "-weight.image": 9,
      "+weight.image": 34,
      "-weight.font": 17,
      "+weight.font": 23,
      "+weight.fontCount": 4,
      "-timeToFirstByte": 5,
      "-totalBlockingTime": 6,
      "-largestContentfulPaint": 16
    },
    "axe": {
      "passes": 689,
      "violations": 4
    }
  },
  {
    "url": "https://www.stellantis.com/fr/actualite/communiques-de-presse/2021/juin/le-cern-pose-la-premiere-pierre-du-portail-de-la-science",
    "requestedUrl": "https://www.stellantis.com/fr/actualite/communiques-de-presse/2021/juin/le-cern-pose-la-premiere-pierre-du-portail-de-la-science",
    "timestamp": 1707633619476,
    "ranks": {
      "hundos": 27,
      "performance": 34,
      "accessibility": 17,
      "cumulative": 27
    },
    "lighthouse": {
      "version": "11.5.0",
      "performance": 0.7,
      "accessibility": 0.98,
      "bestPractices": 0.81,
      "seo": 0.91,
      "total": 340
    },
    "firstContentfulPaint": 2659.5510000000004,
    "firstMeaningfulPaint": 2659.5510000000004,
    "speedIndex": 3950.559677011364,
    "largestContentfulPaint": 6159.380999999999,
    "totalBlockingTime": 45,
    "cumulativeLayoutShift": 0.09282548730871593,
    "timeToInteractive": 9122.3805,
    "maxPotentialFirstInputDelay": 107,
    "timeToFirstByte": 23.070000000000007,
    "weight": {
      "summary": "56 requests • 1,4 MiB",
      "total": 1480881,
      "image": 713938,
      "imageCount": 8,
      "script": 203425,
      "scriptCount": 10,
      "document": 195903,
      "font": 244863,
      "fontCount": 16,
      "stylesheet": 57104,
      "stylesheetCount": 9,
      "thirdParty": 633544,
      "thirdPartyCount": 8
    },
    "run": {
      "number": 2,
      "total": 3
    },
    "sidequests": {
      "-weight.total": 27,
      "+weight.total": 21,
      "-weight.document": 38,
      "+weight.document": 10,
      "-weight.script": 27,
      "+weight.script": 8,
      "-weight.image": 23,
      "+weight.image": 20,
      "-weight.font": 28,
      "+weight.font": 12,
      "+weight.fontCount": 3,
      "-timeToFirstByte": 17,
      "-totalBlockingTime": 11,
      "-largestContentfulPaint": 18
    },
    "axe": {
      "passes": 719,
      "violations": 4
    }
  },
  {
    "url": "https://www.stellantis.com/fr/fca-psa-archives/psa/rapports-rse",
    "requestedUrl": "https://www.stellantis.com/fr/fca-psa-archives/psa/rapports-rse",
    "timestamp": 1707634267185,
    "ranks": {
      "hundos": 29,
      "performance": 10,
      "accessibility": 5,
      "cumulative": 28
    },
    "lighthouse": {
      "version": "11.5.0",
      "performance": 0.74,
      "accessibility": 1,
      "bestPractices": 0.81,
      "seo": 0.84,
      "total": 339
    },
    "firstContentfulPaint": 2524.9089999999997,
    "firstMeaningfulPaint": 2524.9089999999997,
    "speedIndex": 3375.110327869311,
    "largestContentfulPaint": 6018.348999999999,
    "totalBlockingTime": 57.00000000000091,
    "cumulativeLayoutShift": 0.00437375332163872,
    "timeToInteractive": 8267.935,
    "maxPotentialFirstInputDelay": 149,
    "timeToFirstByte": 40.104,
    "weight": {
      "summary": "44 requests • 1,1 MiB",
      "total": 1124188,
      "image": 414349,
      "imageCount": 3,
      "script": 203423,
      "scriptCount": 10,
      "document": 189380,
      "font": 195445,
      "fontCount": 13,
      "stylesheet": 57102,
      "stylesheetCount": 9,
      "thirdParty": 582967,
      "thirdPartyCount": 7
    },
    "run": {
      "number": 3,
      "total": 3
    },
    "sidequests": {
      "-weight.total": 2,
      "+weight.total": 46,
      "-weight.document": 2,
      "+weight.document": 46,
      "-weight.script": 25,
      "+weight.script": 10,
      "-weight.image": 2,
      "+weight.image": 41,
      "-weight.font": 4,
      "+weight.font": 36,
      "+weight.fontCount": 6,
      "-timeToFirstByte": 28,
      "-totalBlockingTime": 16,
      "-largestContentfulPaint": 13
    },
    "axe": {
      "passes": 570,
      "violations": 3
    }
  },
  {
    "url": "https://www.stellantis.com/fr/actualite/communiques-de-presse/2021/juillet/ned-curic-va-rejoindre-stellantis-en-tant-que-chief-technology-officer",
    "requestedUrl": "https://www.stellantis.com/fr/actualite/communiques-de-presse/2021/juillet/ned-curic-va-rejoindre-stellantis-en-tant-que-chief-technology-officer",
    "timestamp": 1707633077631,
    "ranks": {
      "hundos": 30,
      "performance": 37,
      "accessibility": 28,
      "cumulative": 29
    },
    "lighthouse": {
      "version": "11.5.0",
      "performance": 0.69,
      "accessibility": 0.98,
      "bestPractices": 0.81,
      "seo": 0.91,
      "total": 339
    },
    "firstContentfulPaint": 2310.264,
    "firstMeaningfulPaint": 2310.264,
    "speedIndex": 3801.471996315324,
    "largestContentfulPaint": 6612.8330000000005,
    "totalBlockingTime": 38,
    "cumulativeLayoutShift": 0.1185800829282143,
    "timeToInteractive": 7261.3730000000005,
    "maxPotentialFirstInputDelay": 108,
    "timeToFirstByte": 43.464000000000006,
    "weight": {
      "summary": "52 requests • 1,3 MiB",
      "total": 1347108,
      "image": 583565,
      "imageCount": 8,
      "script": 203234,
      "scriptCount": 10,
      "document": 192094,
      "font": 246702,
      "fontCount": 16,
      "stylesheet": 57101,
      "stylesheetCount": 9,
      "thirdParty": 633959,
      "thirdPartyCount": 7
    },
    "run": {
      "number": 1,
      "total": 3
    },
    "sidequests": {
      "-weight.total": 25,
      "+weight.total": 23,
      "-weight.document": 20,
      "+weight.document": 28,
      "-weight.script": 1,
      "+weight.script": 34,
      "-weight.image": 19,
      "+weight.image": 24,
      "-weight.font": 34,
      "+weight.font": 6,
      "+weight.fontCount": 3,
      "-timeToFirstByte": 36,
      "-totalBlockingTime": 4,
      "-largestContentfulPaint": 31
    },
    "axe": {
      "passes": 688,
      "violations": 4
    }
  },
  {
    "url": "https://www.stellantis.com/fr/finance/informations-bourse-et-actionnaires/distribution-information/2023-ordinary-distribution",
    "requestedUrl": "https://www.stellantis.com/fr/finance/informations-bourse-et-actionnaires/distribution-information/2023-ordinary-distribution",
    "timestamp": 1707633293958,
    "ranks": {
      "hundos": 28,
      "performance": 32,
      "accessibility": 37,
      "cumulative": 30
    },
    "lighthouse": {
      "version": "11.5.0",
      "performance": 0.71,
      "accessibility": 0.96,
      "bestPractices": 0.81,
      "seo": 0.91,
      "total": 339
    },
    "firstContentfulPaint": 2487.294,
    "firstMeaningfulPaint": 2487.294,
    "speedIndex": 3820.2570746945853,
    "largestContentfulPaint": 6580.624,
    "totalBlockingTime": 39,
    "cumulativeLayoutShift": 0.07139792704745584,
    "timeToInteractive": 6995.164,
    "maxPotentialFirstInputDelay": 108,
    "timeToFirstByte": 17.729000000000006,
    "weight": {
      "summary": "47 requests • 1,3 MiB",
      "total": 1326066,
      "image": 608958,
      "imageCount": 6,
      "script": 203313,
      "scriptCount": 10,
      "document": 194239,
      "font": 198064,
      "fontCount": 13,
      "stylesheet": 57097,
      "stylesheetCount": 9,
      "thirdParty": 585383,
      "thirdPartyCount": 7
    },
    "run": {
      "number": 2,
      "total": 3
    },
    "sidequests": {
      "-weight.total": 24,
      "+weight.total": 24,
      "-weight.document": 32,
      "+weight.document": 16,
      "-weight.script": 5,
      "+weight.script": 30,
      "-weight.image": 20,
      "+weight.image": 23,
      "-weight.font": 6,
      "+weight.font": 34,
      "+weight.fontCount": 6,
      "-timeToFirstByte": 13,
      "-totalBlockingTime": 6,
      "-largestContentfulPaint": 28
    },
    "axe": {
      "passes": 1016,
      "violations": 43
    }
  },
  {
    "url": "https://www.stellantis.com/fr/actualite/communiques-de-presse/2022/mars/dare-forward-2030-le-plan-strategique-de-stellantis-pour-une-liberte-de-mouvement-d-avant-garde",
    "requestedUrl": "https://www.stellantis.com/fr/actualite/communiques-de-presse/2022/mars/dare-forward-2030-le-plan-strategique-de-stellantis-pour-une-liberte-de-mouvement-d-avant-garde",
    "timestamp": 1707634087054,
    "ranks": {
      "hundos": 31,
      "performance": 38,
      "accessibility": 9,
      "cumulative": 31
    },
    "lighthouse": {
      "version": "11.5.0",
      "performance": 0.68,
      "accessibility": 0.98,
      "bestPractices": 0.81,
      "seo": 0.91,
      "total": 338
    },
    "firstContentfulPaint": 2475.6659999999997,
    "firstMeaningfulPaint": 2475.6659999999997,
    "speedIndex": 3434.7031974990423,
    "largestContentfulPaint": 5677.781999999999,
    "totalBlockingTime": 50,
    "cumulativeLayoutShift": 0.15223217451961185,
    "timeToInteractive": 7655.685000000001,
    "maxPotentialFirstInputDelay": 110,
    "timeToFirstByte": 49.899,
    "weight": {
      "summary": "56 requests • 1,2 MiB",
      "total": 1208573,
      "image": 440768,
      "imageCount": 8,
      "script": 203357,
      "scriptCount": 10,
      "document": 196835,
      "font": 244857,
      "fontCount": 16,
      "stylesheet": 57101,
      "stylesheetCount": 9,
      "thirdParty": 633487,
      "thirdPartyCount": 8
    },
    "run": {
      "number": 3,
      "total": 3
    },
    "sidequests": {
      "-weight.total": 19,
      "+weight.total": 29,
      "-weight.document": 41,
      "+weight.document": 7,
      "-weight.script": 8,
      "+weight.script": 27,
      "-weight.image": 12,
      "+weight.image": 31,
      "-weight.font": 25,
      "+weight.font": 15,
      "+weight.fontCount": 3,
      "-timeToFirstByte": 42,
      "-totalBlockingTime": 12,
      "-largestContentfulPaint": 1
    },
    "axe": {
      "passes": 881,
      "violations": 4
    }
  },
  {
    "url": "https://www.stellantis.com/fr/actualite/communiques-de-presse/2023/fevrier/stellantis-annonce-un-investissement-strategique-dans-le-cuivre-en-argentine-et-renouvelle-son-engagement-d-atteindre-la-neutralite-carbone-d-ici-2038",
    "requestedUrl": "https://www.stellantis.com/fr/actualite/communiques-de-presse/2023/fevrier/stellantis-annonce-un-investissement-strategique-dans-le-cuivre-en-argentine-et-renouvelle-son-engagement-d-atteindre-la-neutralite-carbone-d-ici-2038",
    "timestamp": 1707632908814,
    "ranks": {
      "hundos": 34,
      "performance": 21,
      "accessibility": 38,
      "cumulative": 32
    },
    "lighthouse": {
      "version": "11.5.0",
      "performance": 0.72,
      "accessibility": 0.94,
      "bestPractices": 0.81,
      "seo": 0.91,
      "total": 338
    },
    "firstContentfulPaint": 2743.686,
    "firstMeaningfulPaint": 2743.686,
    "speedIndex": 2951.8485043903806,
    "largestContentfulPaint": 6525.806000000001,
    "totalBlockingTime": 68,
    "cumulativeLayoutShift": 0.03525081399024555,
    "timeToInteractive": 7879.696,
    "maxPotentialFirstInputDelay": 149,
    "timeToFirstByte": 63.409000000000006,
    "weight": {
      "summary": "58 requests • 4,3 MiB",
      "total": 4489654,
      "image": 3707086,
      "imageCount": 9,
      "script": 203407,
      "scriptCount": 10,
      "document": 195671,
      "font": 260695,
      "fontCount": 17,
      "stylesheet": 57098,
      "stylesheetCount": 9,
      "thirdParty": 649422,
      "thirdPartyCount": 8
    },
    "run": {
      "number": 1,
      "total": 3
    },
    "sidequests": {
      "-weight.total": 38,
      "+weight.total": 10,
      "-weight.document": 37,
      "+weight.document": 11,
      "-weight.script": 13,
      "+weight.script": 22,
      "-weight.image": 33,
      "+weight.image": 10,
      "-weight.font": 37,
      "+weight.font": 3,
      "+weight.fontCount": 2,
      "-timeToFirstByte": 45,
      "-totalBlockingTime": 27,
      "-largestContentfulPaint": 26
    },
    "axe": {
      "passes": 733,
      "violations": 5
    }
  },
  {
    "url": "https://www.stellantis.com/fr/actualite/communiques-de-presse/2022/juin/la-transformation-en-action-le-pole-industriel-francais-tremery-metz-soutient-l-electrification-des-vehicules-de-stellantis",
    "requestedUrl": "https://www.stellantis.com/fr/actualite/communiques-de-presse/2022/juin/la-transformation-en-action-le-pole-industriel-francais-tremery-metz-soutient-l-electrification-des-vehicules-de-stellantis",
    "timestamp": 1707633513413,
    "ranks": {
      "hundos": 33,
      "performance": 18,
      "accessibility": 41,
      "cumulative": 33
    },
    "lighthouse": {
      "version": "11.5.0",
      "performance": 0.73,
      "accessibility": 0.94,
      "bestPractices": 0.81,
      "seo": 0.9,
      "total": 338
    },
    "firstContentfulPaint": 2499.7724999999996,
    "firstMeaningfulPaint": 2499.7724999999996,
    "speedIndex": 4029.497380911378,
    "largestContentfulPaint": 6019.988500000001,
    "totalBlockingTime": 31,
    "cumulativeLayoutShift": 0.01344041104535151,
    "timeToInteractive": 9187.926499999998,
    "maxPotentialFirstInputDelay": 105,
    "timeToFirstByte": 36.836,
    "weight": {
      "summary": "60 requests • 7,9 MiB",
      "total": 8283663,
      "image": 7500111,
      "imageCount": 11,
      "script": 203417,
      "scriptCount": 10,
      "document": 196620,
      "font": 260695,
      "fontCount": 17,
      "stylesheet": 57102,
      "stylesheetCount": 9,
      "thirdParty": 649448,
      "thirdPartyCount": 8
    },
    "run": {
      "number": 2,
      "total": 3
    },
    "sidequests": {
      "-weight.total": 45,
      "+weight.total": 3,
      "-weight.document": 40,
      "+weight.document": 8,
      "-weight.script": 21,
      "+weight.script": 14,
      "-weight.image": 40,
      "+weight.image": 3,
      "-weight.font": 37,
      "+weight.font": 3,
      "+weight.fontCount": 2,
      "-timeToFirstByte": 24,
      "-totalBlockingTime": 1,
      "-largestContentfulPaint": 14
    },
    "axe": {
      "passes": 796,
      "violations": 7
    }
  },
  {
    "url": "https://www.stellantis.com/fr/actualite/communiques-de-presse/2023/avril/le-tout-nouveau-ram-1500-rev-electrique-2025-avec-une-autonomie-cible-de-plus-de-800-km-devoile-au-salon-international-de-l-auto-de-new-york",
    "requestedUrl": "https://www.stellantis.com/fr/actualite/communiques-de-presse/2023/avril/le-tout-nouveau-ram-1500-rev-electrique-2025-avec-une-autonomie-cible-de-plus-de-800-km-devoile-au-salon-international-de-l-auto-de-new-york",
    "timestamp": 1707633951472,
    "ranks": {
      "hundos": 32,
      "performance": 23,
      "accessibility": 42,
      "cumulative": 34
    },
    "lighthouse": {
      "version": "11.5.0",
      "performance": 0.72,
      "accessibility": 0.94,
      "bestPractices": 0.81,
      "seo": 0.91,
      "total": 338
    },
    "firstContentfulPaint": 2460.325,
    "firstMeaningfulPaint": 2460.325,
    "speedIndex": 3208.0157936480496,
    "largestContentfulPaint": 6889.639,
    "totalBlockingTime": 60,
    "cumulativeLayoutShift": 0.053630289040495396,
    "timeToInteractive": 7469.073,
    "maxPotentialFirstInputDelay": 151,
    "timeToFirstByte": 18.658,
    "weight": {
      "summary": "57 requests • 3,8 MiB",
      "total": 3950950,
      "image": 3180942,
      "imageCount": 13,
      "script": 203367,
      "scriptCount": 10,
      "document": 198452,
      "font": 246672,
      "fontCount": 16,
      "stylesheet": 57101,
      "stylesheetCount": 9,
      "thirdParty": 634065,
      "thirdPartyCount": 7
    },
    "run": {
      "number": 3,
      "total": 3
    },
    "sidequests": {
      "-weight.total": 35,
      "+weight.total": 13,
      "-weight.document": 42,
      "+weight.document": 6,
      "-weight.script": 11,
      "+weight.script": 24,
      "-weight.image": 31,
      "+weight.image": 12,
      "-weight.font": 33,
      "+weight.font": 7,
      "+weight.fontCount": 3,
      "-timeToFirstByte": 14,
      "-totalBlockingTime": 18,
      "-largestContentfulPaint": 35
    },
    "axe": {
      "passes": 768,
      "violations": 9
    }
  },
  {
    "url": "https://www.stellantis.com/fr/actualite/communiques-de-presse/2022/janvier/stellantis-a-ameliore-ses-performances-commerciales-en-chine-en-2021",
    "requestedUrl": "https://www.stellantis.com/fr/actualite/communiques-de-presse/2022/janvier/stellantis-a-ameliore-ses-performances-commerciales-en-chine-en-2021",
    "timestamp": 1707633565308,
    "ranks": {
      "hundos": 35,
      "performance": 39,
      "accessibility": 22,
      "cumulative": 35
    },
    "lighthouse": {
      "version": "11.5.0",
      "performance": 0.67,
      "accessibility": 0.98,
      "bestPractices": 0.81,
      "seo": 0.91,
      "total": 337
    },
    "firstContentfulPaint": 2499.415,
    "firstMeaningfulPaint": 2499.415,
    "speedIndex": 3275.4404078623384,
    "largestContentfulPaint": 23196.915,
    "totalBlockingTime": 61,
    "cumulativeLayoutShift": 0.11338305639608504,
    "timeToInteractive": 7399.414999999999,
    "maxPotentialFirstInputDelay": 148,
    "timeToFirstByte": 32.888000000000005,
    "weight": {
      "summary": "52 requests • 4,1 MiB",
      "total": 4300136,
      "image": 3533886,
      "imageCount": 8,
      "script": 203426,
      "scriptCount": 10,
      "document": 194581,
      "font": 246671,
      "fontCount": 16,
      "stylesheet": 57105,
      "stylesheetCount": 9,
      "thirdParty": 634169,
      "thirdPartyCount": 7
    },
    "run": {
      "number": 2,
      "total": 3
    },
    "sidequests": {
      "-weight.total": 37,
      "+weight.total": 11,
      "-weight.document": 34,
      "+weight.document": 14,
      "-weight.script": 28,
      "+weight.script": 7,
      "-weight.image": 32,
      "+weight.image": 11,
      "-weight.font": 32,
      "+weight.font": 8,
      "+weight.fontCount": 3,
      "-timeToFirstByte": 19,
      "-totalBlockingTime": 19,
      "-largestContentfulPaint": 47
    },
    "axe": {
      "passes": 697,
      "violations": 4
    }
  },
  {
    "url": "https://www.stellantis.com/fr/actualite/communiques-de-presse/2021/decembre/ces-2022-stellantis-presente-ses-technologies-avancees-pour-la-mobilite-de-demain-avec-des-experiences-phygitales",
    "requestedUrl": "https://www.stellantis.com/fr/actualite/communiques-de-presse/2021/decembre/ces-2022-stellantis-presente-ses-technologies-avancees-pour-la-mobilite-de-demain-avec-des-experiences-phygitales",
    "timestamp": 1707633047027,
    "ranks": {
      "hundos": 36,
      "performance": 40,
      "accessibility": 10,
      "cumulative": 36
    },
    "lighthouse": {
      "version": "11.5.0",
      "performance": 0.67,
      "accessibility": 0.98,
      "bestPractices": 0.81,
      "seo": 0.91,
      "total": 337
    },
    "firstContentfulPaint": 3009.6409999999996,
    "firstMeaningfulPaint": 3078.1409999999996,
    "speedIndex": 5047.629778989392,
    "largestContentfulPaint": 6797.765,
    "totalBlockingTime": 124.5,
    "cumulativeLayoutShift": 0.0011026329405507385,
    "timeToInteractive": 8882.2835,
    "maxPotentialFirstInputDelay": 137,
    "timeToFirstByte": 52.075,
    "weight": {
      "summary": "55 requests • 5,0 MiB",
      "total": 5255934,
      "image": 4489635,
      "imageCount": 11,
      "script": 203417,
      "scriptCount": 10,
      "document": 194667,
      "font": 246669,
      "fontCount": 16,
      "stylesheet": 57053,
      "stylesheetCount": 9,
      "thirdParty": 634151,
      "thirdPartyCount": 7
    },
    "run": {
      "number": 1,
      "total": 3
    },
    "sidequests": {
      "-weight.total": 42,
      "+weight.total": 6,
      "-weight.document": 35,
      "+weight.document": 13,
      "-weight.script": 21,
      "+weight.script": 14,
      "-weight.image": 37,
      "+weight.image": 6,
      "-weight.font": 31,
      "+weight.font": 9,
      "+weight.fontCount": 3,
      "-timeToFirstByte": 44,
      "-totalBlockingTime": 35,
      "-largestContentfulPaint": 34
    },
    "axe": {
      "passes": 828,
      "violations": 4
    }
  },
  {
    "url": "https://www.stellantis.com/fr/actualite/communiques-de-presse/2023/july/stellantis-investit-dans-un-nouveau-green-campus-a-mirafiori-en-italie",
    "requestedUrl": "https://www.stellantis.com/fr/actualite/communiques-de-presse/2023/july/stellantis-investit-dans-un-nouveau-green-campus-a-mirafiori-en-italie",
    "timestamp": 1707633387634,
    "ranks": {
      "hundos": 37,
      "performance": 35,
      "accessibility": 40,
      "cumulative": 37
    },
    "lighthouse": {
      "version": "11.5.0",
      "performance": 0.69,
      "accessibility": 0.94,
      "bestPractices": 0.81,
      "seo": 0.91,
      "total": 335
    },
    "firstContentfulPaint": 2815.946,
    "firstMeaningfulPaint": 2815.946,
    "speedIndex": 2952.370877645218,
    "largestContentfulPaint": 8134.080999999998,
    "totalBlockingTime": 57,
    "cumulativeLayoutShift": 0.09093881964665836,
    "timeToInteractive": 7559.807000000001,
    "maxPotentialFirstInputDelay": 147,
    "timeToFirstByte": 34.587,
    "weight": {
      "summary": "55 requests • 2,0 MiB",
      "total": 2050582,
      "image": 1271110,
      "imageCount": 10,
      "script": 203416,
      "scriptCount": 10,
      "document": 193790,
      "font": 260693,
      "fontCount": 17,
      "stylesheet": 57104,
      "stylesheetCount": 9,
      "thirdParty": 648195,
      "thirdPartyCount": 7
    },
    "run": {
      "number": 2,
      "total": 3
    },
    "sidequests": {
      "-weight.total": 31,
      "+weight.total": 17,
      "-weight.document": 31,
      "+weight.document": 17,
      "-weight.script": 20,
      "+weight.script": 15,
      "-weight.image": 27,
      "+weight.image": 16,
      "-weight.font": 36,
      "+weight.font": 4,
      "+weight.fontCount": 2,
      "-timeToFirstByte": 21,
      "-totalBlockingTime": 15,
      "-largestContentfulPaint": 38
    },
    "axe": {
      "passes": 759,
      "violations": 6
    }
  },
  {
    "url": "https://www.stellantis.com/fr",
    "requestedUrl": "https://www.stellantis.com/fr",
    "timestamp": 1707632687175,
    "ranks": {
      "hundos": 38,
      "performance": 41,
      "accessibility": 36,
      "cumulative": 38
    },
    "lighthouse": {
      "version": "11.5.0",
      "performance": 0.66,
      "accessibility": 0.96,
      "bestPractices": 0.81,
      "seo": 0.91,
      "total": 334
    },
    "firstContentfulPaint": 2518.375,
    "firstMeaningfulPaint": 2518.375,
    "speedIndex": 6500.264222197133,
    "largestContentfulPaint": 11679.412999999999,
    "totalBlockingTime": 39.5,
    "cumulativeLayoutShift": 0.014611021748662764,
    "timeToInteractive": 7665.809000000001,
    "maxPotentialFirstInputDelay": 110,
    "timeToFirstByte": 14.6550000000002,
    "weight": {
      "summary": "61 requests • 7,2 MiB",
      "total": 7503714,
      "image": 6807900,
      "imageCount": 17,
      "script": 203421,
      "scriptCount": 10,
      "document": 191458,
      "font": 178156,
      "fontCount": 12,
      "stylesheet": 57080,
      "stylesheetCount": 9,
      "thirdParty": 566861,
      "thirdPartyCount": 8
    },
    "run": {
      "number": 1,
      "total": 3
    },
    "sidequests": {
      "-weight.total": 44,
      "+weight.total": 4,
      "-weight.document": 13,
      "+weight.document": 35,
      "-weight.script": 23,
      "+weight.script": 12,
      "-weight.image": 39,
      "+weight.image": 4,
      "-weight.font": 1,
      "+weight.font": 39,
      "+weight.fontCount": 7,
      "-timeToFirstByte": 1,
      "-totalBlockingTime": 7,
      "-largestContentfulPaint": 42
    },
    "axe": {
      "passes": 778,
      "violations": 6
    }
  },
  {
    "url": "https://www.stellantis.com/fr/marques/vauxhall",
    "requestedUrl": "https://www.stellantis.com/fr/marques/vauxhall",
    "timestamp": 1707633796925,
    "ranks": {
      "hundos": 39,
      "performance": 43,
      "accessibility": 6,
      "cumulative": 39
    },
    "lighthouse": {
      "version": "11.5.0",
      "performance": 0.61,
      "accessibility": 1,
      "bestPractices": 0.81,
      "seo": 0.91,
      "total": 333
    },
    "firstContentfulPaint": 4202.5905,
    "firstMeaningfulPaint": 4277.5905,
    "speedIndex": 6066.619873195742,
    "largestContentfulPaint": 13170.735500000003,
    "totalBlockingTime": 69.5,
    "cumulativeLayoutShift": 0.0003486984814617416,
    "timeToInteractive": 11145.590500000002,
    "maxPotentialFirstInputDelay": 106,
    "timeToFirstByte": 15.667000000000009,
    "weight": {
      "summary": "50 requests • 4,8 MiB",
      "total": 5071410,
      "image": 4324783,
      "imageCount": 7,
      "script": 203426,
      "scriptCount": 10,
      "document": 189316,
      "font": 232288,
      "fontCount": 15,
      "stylesheet": 57108,
      "stylesheetCount": 9,
      "thirdParty": 619812,
      "thirdPartyCount": 7
    },
    "run": {
      "number": 3,
      "total": 3
    },
    "sidequests": {
      "-weight.total": 41,
      "+weight.total": 7,
      "-weight.document": 1,
      "+weight.document": 47,
      "-weight.script": 28,
      "+weight.script": 7,
      "-weight.image": 36,
      "+weight.image": 7,
      "-weight.font": 18,
      "+weight.font": 22,
      "+weight.fontCount": 4,
      "-timeToFirstByte": 3,
      "-totalBlockingTime": 28,
      "-largestContentfulPaint": 43
    },
    "axe": {
      "passes": 541,
      "violations": 3
    }
  },
  {
    "url": "https://www.stellantis.com/fr/actualite/communiques-de-presse/2022/juillet/resultats-semestriels-2022",
    "requestedUrl": "https://www.stellantis.com/fr/actualite/communiques-de-presse/2022/juillet/resultats-semestriels-2022",
    "timestamp": 1707633502253,
    "ranks": {
      "hundos": 40,
      "performance": 44,
      "accessibility": 12,
      "cumulative": 40
    },
    "lighthouse": {
      "version": "11.5.0",
      "performance": 0.59,
      "accessibility": 0.98,
      "bestPractices": 0.81,
      "seo": 0.91,
      "total": 329
    },
    "firstContentfulPaint": 2527.692,
    "firstMeaningfulPaint": 2527.692,
    "speedIndex": 3262.203156728334,
    "largestContentfulPaint": 6370.824000000001,
    "totalBlockingTime": 39.5,
    "cumulativeLayoutShift": 0.27406428658552834,
    "timeToInteractive": 7368.912,
    "maxPotentialFirstInputDelay": 108,
    "timeToFirstByte": 41.762,
    "weight": {
      "summary": "52 requests • 1,1 MiB",
      "total": 1204150,
      "image": 440768,
      "imageCount": 8,
      "script": 203415,
      "scriptCount": 10,
      "document": 193544,
      "font": 244855,
      "fontCount": 16,
      "stylesheet": 57102,
      "stylesheetCount": 9,
      "thirdParty": 632352,
      "thirdPartyCount": 7
    },
    "run": {
      "number": 2,
      "total": 3
    },
    "sidequests": {
      "-weight.total": 16,
      "+weight.total": 32,
      "-weight.document": 29,
      "+weight.document": 19,
      "-weight.script": 19,
      "+weight.script": 16,
      "-weight.image": 12,
      "+weight.image": 31,
      "-weight.font": 23,
      "+weight.font": 17,
      "+weight.fontCount": 3,
      "-timeToFirstByte": 31,
      "-totalBlockingTime": 7,
      "-largestContentfulPaint": 22
    },
    "axe": {
      "passes": 747,
      "violations": 4
    }
  },
  {
    "url": "https://www.stellantis.com/fr/fca-psa-archives/psa/informations-reglementees/2018",
    "requestedUrl": "https://www.stellantis.com/fr/fca-psa-archives/psa/informations-reglementees/2018",
    "timestamp": 1707633195869,
    "ranks": {
      "hundos": 41,
      "performance": 9,
      "accessibility": 45,
      "cumulative": 41
    },
    "lighthouse": {
      "version": "11.5.0",
      "performance": 0.74,
      "accessibility": 0.88,
      "bestPractices": 0.81,
      "seo": 0.84,
      "total": 327
    },
    "firstContentfulPaint": 2509.352,
    "firstMeaningfulPaint": 2509.352,
    "speedIndex": 3349.2738627610297,
    "largestContentfulPaint": 5894.228000000001,
    "totalBlockingTime": 34.5,
    "cumulativeLayoutShift": 0.008099280245286573,
    "timeToInteractive": 8349.358,
    "maxPotentialFirstInputDelay": 107,
    "timeToFirstByte": 51.27799999999999,
    "weight": {
      "summary": "45 requests • 1,1 MiB",
      "total": 1149699,
      "image": 414354,
      "imageCount": 3,
      "script": 203409,
      "scriptCount": 10,
      "document": 189997,
      "font": 220373,
      "fontCount": 14,
      "stylesheet": 57098,
      "stylesheetCount": 9,
      "thirdParty": 607872,
      "thirdPartyCount": 7
    },
    "run": {
      "number": 1,
      "total": 3
    },
    "sidequests": {
      "-weight.total": 4,
      "+weight.total": 44,
      "-weight.document": 5,
      "+weight.document": 43,
      "-weight.script": 14,
      "+weight.script": 21,
      "-weight.image": 3,
      "+weight.image": 40,
      "-weight.font": 10,
      "+weight.font": 30,
      "+weight.fontCount": 5,
      "-timeToFirstByte": 43,
      "-totalBlockingTime": 3,
      "-largestContentfulPaint": 6
    },
    "axe": {
      "passes": 719,
      "violations": 3
    }
  },
  {
    "url": "https://www.stellantis.com/fr/fca-psa-archives/psa/publications-financieres/2016",
    "requestedUrl": "https://www.stellantis.com/fr/fca-psa-archives/psa/publications-financieres/2016",
    "timestamp": 1707633186215,
    "ranks": {
      "hundos": 42,
      "performance": 15,
      "accessibility": 44,
      "cumulative": 42
    },
    "lighthouse": {
      "version": "11.5.0",
      "performance": 0.74,
      "accessibility": 0.88,
      "bestPractices": 0.81,
      "seo": 0.84,
      "total": 327
    },
    "firstContentfulPaint": 2318.9974999999995,
    "firstMeaningfulPaint": 2318.9974999999995,
    "speedIndex": 3649.109441816474,
    "largestContentfulPaint": 5980.5515,
    "totalBlockingTime": 41,
    "cumulativeLayoutShift": 0.004354632234712141,
    "timeToInteractive": 8848.5615,
    "maxPotentialFirstInputDelay": 108,
    "timeToFirstByte": 43.382000000000005,
    "weight": {
      "summary": "49 requests • 1,1 MiB",
      "total": 1152549,
      "image": 414349,
      "imageCount": 3,
      "script": 203242,
      "scriptCount": 10,
      "document": 191801,
      "font": 220378,
      "fontCount": 14,
      "stylesheet": 57103,
      "stylesheetCount": 9,
      "thirdParty": 608905,
      "thirdPartyCount": 8
    },
    "run": {
      "number": 1,
      "total": 3
    },
    "sidequests": {
      "-weight.total": 5,
      "+weight.total": 43,
      "-weight.document": 18,
      "+weight.document": 30,
      "-weight.script": 3,
      "+weight.script": 32,
      "-weight.image": 2,
      "+weight.image": 41,
      "-weight.font": 11,
      "+weight.font": 29,
      "+weight.fontCount": 5,
      "-timeToFirstByte": 35,
      "-totalBlockingTime": 9,
      "-largestContentfulPaint": 11
    },
    "axe": {
      "passes": 872,
      "violations": 3
    }
  },
  {
    "url": "https://www.stellantis.com/fr/actualite/stories/un-brillant-avenir-nous-attend",
    "requestedUrl": "https://www.stellantis.com/fr/actualite/stories/un-brillant-avenir-nous-attend",
    "timestamp": 1707633176412,
    "ranks": {
      "hundos": 43,
      "performance": 42,
      "accessibility": 35,
      "cumulative": 43
    },
    "lighthouse": {
      "version": "11.5.0",
      "performance": 0.62,
      "accessibility": 0.96,
      "bestPractices": 0.59,
      "seo": 0.91,
      "total": 308
    },
    "firstContentfulPaint": 2536.1380000000004,
    "firstMeaningfulPaint": 2536.1380000000004,
    "speedIndex": 6697.300850740761,
    "largestContentfulPaint": 7437.209999999999,
    "totalBlockingTime": 226,
    "cumulativeLayoutShift": 0.0035357511759461463,
    "timeToInteractive": 15844.722,
    "maxPotentialFirstInputDelay": 161,
    "timeToFirstByte": 44.82299999999999,
    "weight": {
      "summary": "69 requests • 2,4 MiB",
      "total": 2467844,
      "image": 682101,
      "imageCount": 9,
      "script": 1134217,
      "scriptCount": 15,
      "document": 234301,
      "font": 204513,
      "fontCount": 14,
      "stylesheet": 105119,
      "stylesheetCount": 10,
      "thirdParty": 1696041,
      "thirdPartyCount": 11
    },
    "run": {
      "number": 1,
      "total": 3
    },
    "sidequests": {
      "-weight.total": 33,
      "+weight.total": 15,
      "-weight.document": 45,
      "+weight.document": 3,
      "-weight.script": 32,
      "+weight.script": 3,
      "-weight.image": 22,
      "+weight.image": 21,
      "-weight.font": 7,
      "+weight.font": 33,
      "+weight.fontCount": 5,
      "-timeToFirstByte": 38,
      "-totalBlockingTime": 36,
      "-largestContentfulPaint": 36
    },
    "axe": {
      "passes": 678,
      "violations": 5
    }
  },
  {
    "url": "https://www.stellantis.com/fr/actualite/communiques-de-presse/2022/avril/stellantis-contribue-a-des-essais-de-vehicules-connectes-5g-aux-etats-unis-permettant-d-alerter-en-temps-reel-d-un-danger-imminent",
    "requestedUrl": "https://www.stellantis.com/fr/actualite/communiques-de-presse/2022/avril/stellantis-contribue-a-des-essais-de-vehicules-connectes-5g-aux-etats-unis-permettant-d-alerter-en-temps-reel-d-un-danger-imminent",
    "timestamp": 1707633014347,
    "ranks": {
      "hundos": 44,
      "performance": 45,
      "accessibility": 39,
      "cumulative": 44
    },
    "lighthouse": {
      "version": "11.5.0",
      "performance": 0.59,
      "accessibility": 0.94,
      "bestPractices": 0.59,
      "seo": 0.91,
      "total": 303
    },
    "firstContentfulPaint": 2518.350000000001,
    "firstMeaningfulPaint": 2518.350000000001,
    "speedIndex": 7120.415594250162,
    "largestContentfulPaint": 6328.3,
    "totalBlockingTime": 245,
    "cumulativeLayoutShift": 0.1224332002832958,
    "timeToInteractive": 16903.362999999998,
    "maxPotentialFirstInputDelay": 165,
    "timeToFirstByte": 38.892999999999994,
    "weight": {
      "summary": "72 requests • 3,8 MiB",
      "total": 4009810,
      "image": 2162579,
      "imageCount": 12,
      "script": 1134108,
      "scriptCount": 15,
      "document": 235054,
      "font": 266628,
      "fontCount": 18,
      "stylesheet": 105116,
      "stylesheetCount": 10,
      "thirdParty": 1854726,
      "thirdPartyCount": 10
    },
    "run": {
      "number": 1,
      "total": 3
    },
    "sidequests": {
      "-weight.total": 36,
      "+weight.total": 12,
      "-weight.document": 46,
      "+weight.document": 2,
      "-weight.script": 31,
      "+weight.script": 4,
      "-weight.image": 30,
      "+weight.image": 13,
      "-weight.font": 39,
      "+weight.font": 1,
      "+weight.fontCount": 1,
      "-timeToFirstByte": 26,
      "-totalBlockingTime": 37,
      "-largestContentfulPaint": 21
    },
    "axe": {
      "passes": 809,
      "violations": 6
    }
  },
  {
    "url": "https://www.stellantis.com/fr/groupe/dare-forward-2030",
    "requestedUrl": "https://www.stellantis.com/fr/groupe/dare-forward-2030",
    "timestamp": 1707633230448,
    "ranks": {
      "hundos": 45,
      "performance": 46,
      "accessibility": 43,
      "cumulative": 45
    },
    "lighthouse": {
      "version": "11.5.0",
      "performance": 0.59,
      "accessibility": 0.92,
      "bestPractices": 0.59,
      "seo": 0.91,
      "total": 301
    },
    "firstContentfulPaint": 2343.0480000000002,
    "firstMeaningfulPaint": 2496.8070000000002,
    "speedIndex": 8140.53148487333,
    "largestContentfulPaint": 19806.6945,
    "totalBlockingTime": 260,
    "cumulativeLayoutShift": 0.03778582591268298,
    "timeToInteractive": 22108.9215,
    "maxPotentialFirstInputDelay": 161,
    "timeToFirstByte": 15.701999999999991,
    "weight": {
      "summary": "72 requests • 15,6 MiB",
      "total": 16353914,
      "image": 14553201,
      "imageCount": 15,
      "script": 1134248,
      "scriptCount": 15,
      "document": 235206,
      "font": 219825,
      "fontCount": 15,
      "stylesheet": 105120,
      "stylesheetCount": 10,
      "thirdParty": 1773237,
      "thirdPartyCount": 10
    },
    "run": {
      "number": 2,
      "total": 3
    },
    "sidequests": {
      "-weight.total": 47,
      "+weight.total": 1,
      "-weight.document": 47,
      "+weight.document": 1,
      "-weight.script": 33,
      "+weight.script": 2,
      "-weight.image": 42,
      "+weight.image": 1,
      "-weight.font": 9,
      "+weight.font": 31,
      "+weight.fontCount": 4,
      "-timeToFirstByte": 4,
      "-totalBlockingTime": 38,
      "-largestContentfulPaint": 46
    },
    "axe": {
      "passes": 861,
      "violations": 6
    }
  },
  {
    "url": "https://www.stellantis.com/fr/actualite/stories/la-conception-au-service-de-la-mobilite-electrique",
    "requestedUrl": "https://www.stellantis.com/fr/actualite/stories/la-conception-au-service-de-la-mobilite-electrique",
    "timestamp": 1707633165580,
    "ranks": {
      "hundos": 46,
      "performance": 47,
      "accessibility": 46,
      "cumulative": 46
    },
    "lighthouse": {
      "version": "11.5.0",
      "performance": 0.53,
      "accessibility": 0.86,
      "bestPractices": 0.59,
      "seo": 0.91,
      "total": 289
    },
    "firstContentfulPaint": 2401.665,
    "firstMeaningfulPaint": 2555.086,
    "speedIndex": 7789.635773628654,
    "largestContentfulPaint": 14623.559,
    "totalBlockingTime": 342.5,
    "cumulativeLayoutShift": 0.12271090613247894,
    "timeToInteractive": 16770.246000000003,
    "maxPotentialFirstInputDelay": 160,
    "timeToFirstByte": 43.356,
    "weight": {
      "summary": "80 requests • 10,3 MiB",
      "total": 10777029,
      "image": 8960239,
      "imageCount": 18,
      "script": 1134271,
      "scriptCount": 15,
      "document": 234298,
      "font": 235313,
      "fontCount": 16,
      "stylesheet": 105119,
      "stylesheetCount": 10,
      "thirdParty": 1867216,
      "thirdPartyCount": 11
    },
    "run": {
      "number": 1,
      "total": 3
    },
    "sidequests": {
      "-weight.total": 46,
      "+weight.total": 2,
      "-weight.document": 44,
      "+weight.document": 4,
      "-weight.script": 34,
      "+weight.script": 1,
      "-weight.image": 41,
      "+weight.image": 2,
      "-weight.font": 20,
      "+weight.font": 20,
      "+weight.fontCount": 3,
      "-timeToFirstByte": 34,
      "-totalBlockingTime": 39,
      "-largestContentfulPaint": 44
    },
    "axe": {
      "passes": 768,
      "violations": 9
    }
  },
  {
    "url": "https://www.stellantis.com/fr/actualite/communiques-de-presse/2023/mars/le-freedom-of-mobility-forum-annonce-le-programme-et-les-intervenants-du-debat-du-29-mars",
    "requestedUrl": "https://www.stellantis.com/fr/actualite/communiques-de-presse/2023/mars/le-freedom-of-mobility-forum-annonce-le-programme-et-les-intervenants-du-debat-du-29-mars",
    "timestamp": 1707633429067,
    "ranks": {
      "hundos": 47,
      "performance": 11,
      "accessibility": 47,
      "cumulative": 47
    },
    "lighthouse": {
      "version": "11.5.0",
      "performance": 0.74,
      "accessibility": null,
      "bestPractices": 0.81,
      "seo": 0.91,
      "total": 246
    },
    "firstContentfulPaint": 2427.8200000000006,
    "firstMeaningfulPaint": 2427.8200000000006,
    "speedIndex": 3412.108009205955,
    "largestContentfulPaint": 5681.524000000001,
    "totalBlockingTime": 113.5,
    "cumulativeLayoutShift": 0.0077970236884709635,
    "timeToInteractive": 8401.400499999998,
    "maxPotentialFirstInputDelay": 149,
    "timeToFirstByte": 69.971,
    "weight": {
      "summary": "53 requests • 1,2 MiB",
      "total": 1212685,
      "image": 448176,
      "imageCount": 9,
      "script": 205638,
      "scriptCount": 10,
      "document": 192445,
      "font": 244853,
      "fontCount": 16,
      "stylesheet": 57106,
      "stylesheetCount": 9,
      "thirdParty": 634625,
      "thirdPartyCount": 7
    },
    "run": {
      "number": 2,
      "total": 3
    },
    "sidequests": {
      "-weight.total": 21,
      "+weight.total": 27,
      "-weight.document": 21,
      "+weight.document": 27,
      "-weight.script": 30,
      "+weight.script": 5,
      "-weight.image": 16,
      "+weight.image": 27,
      "-weight.font": 21,
      "+weight.font": 19,
      "+weight.fontCount": 3,
      "-timeToFirstByte": 46,
      "-totalBlockingTime": 33,
      "-largestContentfulPaint": 2
    },
    "axe": {
      "passes": 731,
      "violations": 4
    }
  },
  {
    "url": "https://www.stellantis.com/fr/actualite/communiques-de-presse/2024/janvier/le-freedom-of-mobility-forum-annonce-l-ouverture-de-son-edition-2024-sa-thematique-ses-panelistes-ainsi-que-les-universites-associees-pour-le-debat-annuel-en-direct-qui-aura-lieu-le-3-avril",
    "error": "{\"errno\":-4058,\"code\":\"ENOENT\",\"syscall\":\"open\",\"path\":\"C:\\\\Users\\\\andre\\\\source\\\\_web\\\\scores_cac40\\\\batch\\\\.log\\\\2024-02-11\\\\lighthouse-https-www.stellantis.com-fr-actualite-communiques-de-presse-2024-janvier-le-freedom-of-mobility-forum-annonce-l-ouverture-de-son-edition-2024-sa-thematique-ses-panelistes-ainsi-que-les-universites-associees-pour-le-debat-annuel-en-direct-qui-aura-lieu-le-3-avril-1-of-3.json\"}",
    "sidequests": {
      "-weight.total": 48,
      "+weight.total": 48,
      "-weight.document": 48,
      "+weight.document": 48,
      "-weight.script": 35,
      "+weight.script": 35,
      "-weight.image": 43,
      "+weight.image": 43,
      "-weight.font": 40,
      "+weight.font": 40,
      "+weight.fontCount": 8,
      "-timeToFirstByte": 48,
      "-totalBlockingTime": 40,
      "-largestContentfulPaint": 48
    }
  },
  {
    "url": "https://www.stellantis.com/fr/actualite/communiques-de-presse/2023/octobre/stellantis-devient-actionnaire-strategique-de-leapmotor-avec-un-investissement-de-1-5-milliard-d-euros-et-developpera-l-activite-internationale-des-vehicules-electriques-leapmotor",
    "error": "{\"errno\":-4058,\"code\":\"ENOENT\",\"syscall\":\"open\",\"path\":\"C:\\\\Users\\\\andre\\\\source\\\\_web\\\\scores_cac40\\\\batch\\\\.log\\\\2024-02-11\\\\lighthouse-https-www.stellantis.com-fr-actualite-communiques-de-presse-2023-octobre-stellantis-devient-actionnaire-strategique-de-leapmotor-avec-un-investissement-de-1-5-milliard-d-euros-et-developpera-l-activite-internationale-des-vehicules-electriques-leapmotor-1-of-3.json\"}",
    "sidequests": {
      "-weight.total": 48,
      "+weight.total": 48,
      "-weight.document": 48,
      "+weight.document": 48,
      "-weight.script": 35,
      "+weight.script": 35,
      "-weight.image": 43,
      "+weight.image": 43,
      "-weight.font": 40,
      "+weight.font": 40,
      "+weight.fontCount": 8,
      "-timeToFirstByte": 48,
      "-totalBlockingTime": 40,
      "-largestContentfulPaint": 48
    }
  },
  {
    "url": "https://www.stellantis.com/fr/actualite/communiques-de-presse/2020/octobre/les-conseils-de-fca-et-du-groupe-psa-constatent-les-progres-continus-accomplis-en-vue-de-la-realisation-de-la-fusion-et-approuvent-des-mesures-completaires-concernant-notamment-la-distribution-des-actions-de-faurecia-aux-actionnaires-de-stellantis",
    "error": "{\"errno\":-4058,\"code\":\"ENOENT\",\"syscall\":\"open\",\"path\":\"C:\\\\Users\\\\andre\\\\source\\\\_web\\\\scores_cac40\\\\batch\\\\.log\\\\2024-02-11\\\\lighthouse-https-www.stellantis.com-fr-actualite-communiques-de-presse-2020-octobre-les-conseils-de-fca-et-du-groupe-psa-constatent-les-progres-continus-accomplis-en-vue-de-la-realisation-de-la-fusion-et-approuvent-des-mesures-completaires-concernant-notamment-la-distribution-des-actions-de-faurecia-aux-actionnaires-de-stellantis-1-of-3.json\"}",
    "sidequests": {
      "-weight.total": 48,
      "+weight.total": 48,
      "-weight.document": 48,
      "+weight.document": 48,
      "-weight.script": 35,
      "+weight.script": 35,
      "-weight.image": 43,
      "+weight.image": 43,
      "-weight.font": 40,
      "+weight.font": 40,
      "+weight.fontCount": 8,
      "-timeToFirstByte": 48,
      "-totalBlockingTime": 40,
      "-largestContentfulPaint": 48
    }
  }
]